Workbook

Sheet Planilha1
A1: SEI | B1: GESTOR | C1: OBJETO | D1: EMPRESA | E1: MUNICIPIO | F1: FISCAL NOMEADO | G1: STATUS_original | H1: REGIÃO | I1: STATUS
A2: 150001/012862/2022 | B2: =IFERROR(VLOOKUP(TRIM(A2),[1]Medições!$B$2:$I$48,8,FALSE),VLOOKUP(TRIM(A2),[1]PROBLEMAS!$B$2:$I$122,8,FALSE)) -> AIMAR FILHO | C2: =VLOOKUP(TRIM(Tabela2[[#This Row],[SEI]]),Tabela3[[Processo SEI]:[Objeto]],5,FALSE) -> PROJETOS E OBRAS PARA REFORMA DA SEDE DO TRE-RJ | D2: CONCREJATO | E2: RIO DE JANEIRO | G2: ACEITE DEFINITIVO | H2: ESPECIAIS | I2: =IFERROR(VLOOKUP(TRIM(Tabela2[[#This Row],[SEI]]),[1]Medições!$B$2:$H$48,7,FALSE),Tabela2[[#This Row],[STATUS_original]]) -> ACEITE DEFINITIVO
A3: E-17/026/1514/2019 | B3: =IFERROR(VLOOKUP(TRIM(A3),[1]Medições!$B$2:$I$48,8,FALSE),VLOOKUP(TRIM(A3),[1]PROBLEMAS!$B$2:$I$122,8,FALSE)) -> AIMAR FILHO | C3: =VLOOKUP(TRIM(Tabela2[[#This Row],[SEI]]),Tabela3[[Processo SEI]:[Objeto]],5,FALSE) -> PROJETO EXECUTIVO E OBRA DE COZINHA INDUSTRIAL E SEDE DA 1ª COMPANHIA DO CFAP – RIO DE JANEIRO | D3: VCE | E3: RIO DE JANEIRO | G3: DISTRATO | H3: ESPECIAIS | I3: =IFERROR(VLOOKUP(TRIM(Tabela2[[#This Row],[SEI]]),[1]Medições!$B$2:$H$48,7,FALSE),Tabela2[[#This Row],[STATUS_original]]) -> DISTRATO
A4: 170026/000230/2022 | B4: =IFERROR(VLOOKUP(TRIM(A4),[1]Medições!$B$2:$I$48,8,FALSE),VLOOKUP(TRIM(A4),[1]PROBLEMAS!$B$2:$I$122,8,FALSE)) -> CARLOS FERNANDES | C4: =VLOOKUP(TRIM(Tabela2[[#This Row],[SEI]]),Tabela3[[Processo SEI]:[Objeto]],5,FALSE) -> CANALIZAÇÃO DO CANAL ABEL - NOVA IGUAÇU E QUEIMADOS | D4: DRATEC | E4: NOVA IGUAÇÚ | F4: ARLINDO BASILIO / OSVALDO NETO | G4: #CONCLUIDA | H4: BX | I4: =IFERROR(VLOOKUP(TRIM(Tabela2[[#This Row],[SEI]]),[1]Medições!$B$2:$H$48,7,FALSE),Tabela2[[#This Row],[STATUS_original]]) -> #CONCLUIDA
A5: 460001/000821/2023 | B5: =IFERROR(VLOOKUP(TRIM(A5),[1]Medições!$B$2:$I$48,8,FALSE),VLOOKUP(TRIM(A5),[1]PROBLEMAS!$B$2:$I$122,8,FALSE)) -> CARLOS FERNANDES | C5: =VLOOKUP(TRIM(Tabela2[[#This Row],[SEI]]),Tabela3[[Processo SEI]:[Objeto]],5,FALSE) -> REVESTIMENTO ASFÁLTICO E DRENAGEM NO 2° DISTRITO (Lote 1) – DUQUE DE CAXIAS/RJ (#FUNDO SOBERANO) | D5: LYTORANEA | E5: DUQUE DE CAXIAS | F5: NICHOLAS TAVARES / ARLINDO BASILIO | G5: #CONCLUIDA | H5: BX | I5: =IFERROR(VLOOKUP(TRIM(Tabela2[[#This Row],[SEI]]),[1]Medições!$B$2:$H$48,7,FALSE),Tabela2[[#This Row],[STATUS_original]]) -> #CONCLUIDA
A6: 460001/000827/2023 | B6: =IFERROR(VLOOKUP(TRIM(A6),[1]Medições!$B$2:$I$48,8,FALSE),VLOOKUP(TRIM(A6),[1]PROBLEMAS!$B$2:$I$122,8,FALSE)) -> CARLOS FERNANDES | C6: =VLOOKUP(TRIM(Tabela2[[#This Row],[SEI]]),Tabela3[[Processo SEI]:[Objeto]],5,FALSE) -> REVESTIMENTO ASFÁLTICO E DRENAGEM NO 2° DISTRITO (Lote 2) – DUQUE DE CAXIAS/RJ (#FUNDO SOBERANO) | D6: ÔMEGA | E6: DUQUE DE CAXIAS | F6: NICHOLAS TAVARES / OSVALDO NETO | G6: #CONCLUIDA | H6: BX | I6: =IFERROR(VLOOKUP(TRIM(Tabela2[[#This Row],[SEI]]),[1]Medições!$B$2:$H$48,7,FALSE),Tabela2[[#This Row],[STATUS_original]]) -> #CONCLUIDA
A7: 330018/001213/2022 | B7: =IFERROR(VLOOKUP(TRIM(A7),[1]Medições!$B$2:$I$48,8,FALSE),VLOOKUP(TRIM(A7),[1]PROBLEMAS!$B$2:$I$122,8,FALSE)) -> CARLOS FERNANDES | C7: =VLOOKUP(TRIM(Tabela2[[#This Row],[SEI]]),Tabela3[[Processo SEI]:[Objeto]],5,FALSE) -> PONTE EM CONCRETO PROTENDIDO COM DRENAGEM – BELFORD ROXO/RJ | D7: SEEL | E7: BELFORD ROXO | F7: NICHOLAS TAVARES / OTAVIO FEITOSA | G7: #CONCLUIDA | H7: BX | I7: =IFERROR(VLOOKUP(TRIM(Tabela2[[#This Row],[SEI]]),[1]Medições!$B$2:$H$48,7,FALSE),Tabela2[[#This Row],[STATUS_original]]) -> #CONCLUIDA
A8: 330018/000737/2022 | B8: =IFERROR(VLOOKUP(TRIM(A8),[1]Medições!$B$2:$I$48,8,FALSE),VLOOKUP(TRIM(A8),[1]PROBLEMAS!$B$2:$I$122,8,FALSE)) -> CARLOS FERNANDES | C8: =VLOOKUP(TRIM(Tabela2[[#This Row],[SEI]]),Tabela3[[Processo SEI]:[Objeto]],5,FALSE) -> PROJETO, DRENAGEM E INFRAESTRUTURA - MENDES/RJ | D8: CMHR | E8: MENDES | F8: JOÃO RODRIGUES / LEANDRO RAMOS | G8: #CONCLUIDA | H8: SL | I8: =IFERROR(VLOOKUP(TRIM(Tabela2[[#This Row],[SEI]]),[1]Medições!$B$2:$H$48,7,FALSE),Tabela2[[#This Row],[STATUS_original]]) -> #CONCLUIDA
A9: 330018/000931/2021 | B9: =IFERROR(VLOOKUP(TRIM(A9),[1]Medições!$B$2:$I$48,8,FALSE),VLOOKUP(TRIM(A9),[1]PROBLEMAS!$B$2:$I$122,8,FALSE)) -> CARLOS FERNANDES | C9: =VLOOKUP(TRIM(Tabela2[[#This Row],[SEI]]),Tabela3[[Processo SEI]:[Objeto]],5,FALSE) -> REVITALIZAÇÃO – AV. DOM PEDRO II – PORTO REAL-RJ | D9: COMAL | E9: PORTO REAL | F9: JOÃO RODRIGUES / LEANDRO RAMOS | G9: #CONCLUIDA | H9: SL | I9: =IFERROR(VLOOKUP(TRIM(Tabela2[[#This Row],[SEI]]),[1]Medições!$B$2:$H$48,7,FALSE),Tabela2[[#This Row],[STATUS_original]]) -> #CONCLUIDA
A10: 170026/003250/2021 | B10: =IFERROR(VLOOKUP(TRIM(A10),[1]Medições!$B$2:$I$48,8,FALSE),VLOOKUP(TRIM(A10),[1]PROBLEMAS!$B$2:$I$122,8,FALSE)) -> CARLOS FERNANDES | C10: =VLOOKUP(TRIM(Tabela2[[#This Row],[SEI]]),Tabela3[[Processo SEI]:[Objeto]],5,FALSE) -> RECAPEAMENTO, PAVIMENTAÇÃO E CONTENÇÃO – BARRA MANSA-RJ | D10: LYTORANEA | E10: BARRA MANSA | F10: LUCIANA POSTIÇO / LEANDRO RAMOS | G10: #CONCLUIDA | H10: SL | I10: =IFERROR(VLOOKUP(TRIM(Tabela2[[#This Row],[SEI]]),[1]Medições!$B$2:$H$48,7,FALSE),Tabela2[[#This Row],[STATUS_original]]) -> #CONCLUIDA
A11: E-17/001/2008/2014 | B11: =IFERROR(VLOOKUP(TRIM(A11),[1]Medições!$B$2:$I$48,8,FALSE),VLOOKUP(TRIM(A11),[1]PROBLEMAS!$B$2:$I$122,8,FALSE)) -> CARLOS FERNANDES | C11: =VLOOKUP(TRIM(Tabela2[[#This Row],[SEI]]),Tabela3[[Processo SEI]:[Objeto]],5,FALSE) -> MICRODRENAGEM E PAVIMENTAÇÃO NO BAIRRO AUSTIN - NOVA IGUAÇU | D11: HYDRA | E11: NOVA IGUAÇÚ | F11: NICHOLAS TAVARES | G11: ACEITE DEFINITIVO | H11: BX | I11: =IFERROR(VLOOKUP(TRIM(Tabela2[[#This Row],[SEI]]),[1]Medições!$B$2:$H$48,7,FALSE),Tabela2[[#This Row],[STATUS_original]]) -> ACEITE DEFINITIVO
A12: 330018/000480/2022 | B12: =IFERROR(VLOOKUP(TRIM(A12),[1]Medições!$B$2:$I$48,8,FALSE),VLOOKUP(TRIM(A12),[1]PROBLEMAS!$B$2:$I$122,8,FALSE)) -> CARLOS FERNANDES | C12: =VLOOKUP(TRIM(Tabela2[[#This Row],[SEI]]),Tabela3[[Processo SEI]:[Objeto]],5,FALSE) -> CONTENÇÃO, DRENAGEM E ESTABILIZAÇÃO – SÃO JOSÉ DE UBÁ/RJ | D12: CTESA | E12: SÃO JOSÉ DE UBÁ | F12: CAIO / JOÃO RODRIGUES | G12: ACEITE DEFINITIVO | H12: NT | I12: =IFERROR(VLOOKUP(TRIM(Tabela2[[#This Row],[SEI]]),[1]Medições!$B$2:$H$48,7,FALSE),Tabela2[[#This Row],[STATUS_original]]) -> ACEITE DEFINITIVO
A13: 330018/000982/2021 | B13: =IFERROR(VLOOKUP(TRIM(A13),[1]Medições!$B$2:$I$48,8,FALSE),VLOOKUP(TRIM(A13),[1]PROBLEMAS!$B$2:$I$122,8,FALSE)) -> CARLOS FERNANDES | C13: =VLOOKUP(TRIM(Tabela2[[#This Row],[SEI]]),Tabela3[[Processo SEI]:[Objeto]],5,FALSE) -> ESTABILIZAÇÃO DE ENCOSTA – AV. FERROVIÁRIOS, NOVA FRIBURGO | D13: SOLOTESTE | E13: NOVA FRIBURGO | F13: CAIO / ARLINDO BASILIO | G13: ACEITE DEFINITIVO | H13: NT | I13: =IFERROR(VLOOKUP(TRIM(Tabela2[[#This Row],[SEI]]),[1]Medições!$B$2:$H$48,7,FALSE),Tabela2[[#This Row],[STATUS_original]]) -> ACEITE DEFINITIVO
A14: 170026/000538/2022 | B14: =IFERROR(VLOOKUP(TRIM(A14),[1]Medições!$B$2:$I$48,8,FALSE),VLOOKUP(TRIM(A14),[1]PROBLEMAS!$B$2:$I$122,8,FALSE)) -> CARLOS FERNANDES | C14: =VLOOKUP(TRIM(Tabela2[[#This Row],[SEI]]),Tabela3[[Processo SEI]:[Objeto]],5,FALSE) -> CONTENÇÃO E DRENAGEM EM CASTELÂNEA, PETRÓPOLIS | D14: CONSÓRCIO ECONORTE GEOSONDA | E14: PETROPOLIS | F14: JEHNIFFER PIRES / WASHINGTON | G14: CONCLUIDA | H14: BX | I14: =IFERROR(VLOOKUP(TRIM(Tabela2[[#This Row],[SEI]]),[1]Medições!$B$2:$H$48,7,FALSE),Tabela2[[#This Row],[STATUS_original]]) -> CONCLUIDA
A15: 330018/001303/2022 | B15: =IFERROR(VLOOKUP(TRIM(A15),[1]Medições!$B$2:$I$48,8,FALSE),VLOOKUP(TRIM(A15),[1]PROBLEMAS!$B$2:$I$122,8,FALSE)) -> CARLOS FERNANDES | C15: =VLOOKUP(TRIM(Tabela2[[#This Row],[SEI]]),Tabela3[[Processo SEI]:[Objeto]],5,FALSE) -> DRENAGEM PLUVIAL E PAVIMENTAÇÃO NO BAIRRO MIGUEL COUTO – NOVA IGUAÇU/RJ | D15: CONSTRUTEC | E15: NOVA IGUAÇÚ | F15: NICHOLAS TAVARES / OTAVIO FEITOSA | G15: CONCLUIDA | H15: BX | I15: =IFERROR(VLOOKUP(TRIM(Tabela2[[#This Row],[SEI]]),[1]Medições!$B$2:$H$48,7,FALSE),Tabela2[[#This Row],[STATUS_original]]) -> CONCLUIDA
... A32: 330018/000333/2022 | B32: =IFERROR(VLOOKUP(TRIM(A32),[1]Medições!$B$2:$I$48,8,FALSE),VLOOKUP(TRIM(A32),[1]PROBLEMAS!$B$2:$I$122,8,FALSE)) -> CARLOS FERNANDES | C32: =VLOOKUP(TRIM(Tabela2[[#This Row],[SEI]]),Tabela3[[Processo SEI]:[Objeto]],5,FALSE) -> RECAPEAMENTO DE LOGRADOUROS EM MAGÉ – RJ | D32: GRAVISA | E32: MAGÉ | F32: ARLINDO BASILIO / OSVALDO NETO | G32: SUSPENSA | H32: BX | I32: =IFERROR(VLOOKUP(TRIM(Tabela2[[#This Row],[SEI]]),[1]Medições!$B$2:$H$48,7,FALSE),Tabela2[[#This Row],[STATUS_original]]) -> SUSPENSA
A33: E-17/026/0056/2020 | B33: =IFERROR(VLOOKUP(TRIM(A33),[1]Medições!$B$2:$I$48,8,FALSE),VLOOKUP(TRIM(A33),[1]PROBLEMAS!$B$2:$I$122,8,FALSE)) -> ERICK HYLARIO | C33: =VLOOKUP(TRIM(Tabela2[[#This Row],[SEI]]),Tabela3[[Processo SEI]:[Objeto]],5,FALSE) -> HOSPITAL COVID-19, NO MUNICÍPIO DE NOVA IGUAÇU | D33: BIG FARM | E33: NOVA IGUAÇU | G33: ACEITE DEFINITIVO | H33: ESPECIAIS | I33: =IFERROR(VLOOKUP(TRIM(Tabela2[[#This Row],[SEI]]),[1]Medições!$B$2:$H$48,7,FALSE),Tabela2[[#This Row],[STATUS_original]]) -> ACEITE DEFINITIVO
A34: 330001/000097/2024 | B34: =IFERROR(VLOOKUP(TRIM(A34),[1]Medições!$B$2:$I$48,8,FALSE),VLOOKUP(TRIM(A34),[1]PROBLEMAS!$B$2:$I$122,8,FALSE)) -> ERICK HYLARIO | C34: =VLOOKUP(TRIM(Tabela2[[#This Row],[SEI]]),Tabela3[[Processo SEI]:[Objeto]],5,FALSE) -> CONCLUSÃO DAS OBRAS DA NOVA SEDE DO MIS – RIO DE JANEIRO | D34: CONS.COPACABANA | E34: RIO DE JANEIRO | F34: OSVALDO NETO / DANRLEI GOMES | G34: EXECUÇÃO | H34: ESPECIAIS | I34: =IFERROR(VLOOKUP(TRIM(Tabela2[[#This Row],[SEI]]),[1]Medições!$B$2:$H$48,7,FALSE),Tabela2[[#This Row],[STATUS_original]]) -> EXECUÇÃO
A35: 460001/001918/2023 | B35: =IFERROR(VLOOKUP(TRIM(A35),[1]Medições!$B$2:$I$48,8,FALSE),VLOOKUP(TRIM(A35),[1]PROBLEMAS!$B$2:$I$122,8,FALSE)) -> ERICK HYLARIO | C35: =VLOOKUP(TRIM(Tabela2[[#This Row],[SEI]]),Tabela3[[Processo SEI]:[Objeto]],5,FALSE) -> REFAZIMENTO DAS FACHADAS DO MIS - NOVA SEDE - 2023 | D35: COPACABANA R2X/TANGRAM | E35: RIO DE JANEIRO | F35: HIGOR MARTINS / DANRLEI GOMES | G35: EXECUÇÃO | H35: ESPECIAIS | I35: =IFERROR(VLOOKUP(TRIM(Tabela2[[#This Row],[SEI]]),[1]Medições!$B$2:$H$48,7,FALSE),Tabela2[[#This Row],[STATUS_original]]) -> EXECUÇÃO
A36: 330001/000247/2025 | B36: =IFERROR(VLOOKUP(TRIM(A36),[1]Medições!$B$2:$I$48,8,FALSE),VLOOKUP(TRIM(A36),[1]PROBLEMAS!$B$2:$I$122,8,FALSE)) -> ERICK HYLARIO | C36: =VLOOKUP(TRIM(Tabela2[[#This Row],[SEI]]),Tabela3[[Processo SEI]:[Objeto]],5,FALSE) -> PAINÉIS DE MARCENARIA DO MIS | D36: FAB MIX CONCRETOS | E36: RIO DE JANEIRO | F36: OSVALDO NETO / HIGOR MARTINS | G36: EXECUÇÃO | H36: ESPECIAIS | I36: =IFERROR(VLOOKUP(TRIM(Tabela2[[#This Row],[SEI]]),[1]Medições!$B$2:$H$48,7,FALSE),Tabela2[[#This Row],[STATUS_original]]) -> EXECUÇÃO
A37: 330001/000414/2024 | B37: =IFERROR(VLOOKUP(TRIM(A37),[1]Medições!$B$2:$I$48,8,FALSE),VLOOKUP(TRIM(A37),[1]PROBLEMAS!$B$2:$I$122,8,FALSE)) -> ERICK HYLARIO | C37: =VLOOKUP(TRIM(Tabela2[[#This Row],[SEI]]),Tabela3[[Processo SEI]:[Objeto]],5,FALSE) -> RECUPERAÇÃO DE EQUIPAMENTOS DO TELEFÉRICO DO ALEMÃO - RJ | D37: MPE | E37: RIO DE JANEIRO | F37: HIGOR MARTINS / DANRLEI GOMES | G37: EXECUÇÃO | H37: ESPECIAIS | I37: =IFERROR(VLOOKUP(TRIM(Tabela2[[#This Row],[SEI]]),[1]Medições!$B$2:$H$48,7,FALSE),Tabela2[[#This Row],[STATUS_original]]) -> EXECUÇÃO
A38: 460001/000779/2023 | B38: =IFERROR(VLOOKUP(TRIM(A38),[1]Medições!$B$2:$I$48,8,FALSE),VLOOKUP(TRIM(A38),[1]PROBLEMAS!$B$2:$I$122,8,FALSE)) -> ERICK HYLARIO | C38: =VLOOKUP(TRIM(Tabela2[[#This Row],[SEI]]),Tabela3[[Processo SEI]:[Objeto]],5,FALSE) -> RECUPERAÇÃO DO TÚNEL EXTRAVASOR EM PETRÓPOLIS | D38: ENGEPRAT | E38: PETRÓPOLIS | G38: ACEITE PROVISORIO | H38: ESPECIAIS | I38: =IFERROR(VLOOKUP(TRIM(Tabela2[[#This Row],[SEI]]),[1]Medições!$B$2:$H$48,7,FALSE),Tabela2[[#This Row],[STATUS_original]]) -> ACEITE PROVISORIO
A39: 170026/000233/2022 | B39: =IFERROR(VLOOKUP(TRIM(A39),[1]Medições!$B$2:$I$48,8,FALSE),VLOOKUP(TRIM(A39),[1]PROBLEMAS!$B$2:$I$122,8,FALSE)) -> ERICK HYLARIO | C39: =VLOOKUP(TRIM(Tabela2[[#This Row],[SEI]]),Tabela3[[Processo SEI]:[Objeto]],5,FALSE) -> CONCLUSÃO DO HOSPITAL DE ONCOLOGIA EM NOVA FRIBURGO | D39: MPE | E39: NOVA FRIBURGO | F39: DANRLEI GOMES / IZADORA COE | G39: EXECUÇÃO | H39: ESPECIAIS | I39: =IFERROR(VLOOKUP(TRIM(Tabela2[[#This Row],[SEI]]),[1]Medições!$B$2:$H$48,7,FALSE),Tabela2[[#This Row],[STATUS_original]]) -> EXECUÇÃO
A40: 170026/001756/2021 | B40: =IFERROR(VLOOKUP(TRIM(A40),[1]Medições!$B$2:$I$48,8,FALSE),VLOOKUP(TRIM(A40),[1]PROBLEMAS!$B$2:$I$122,8,FALSE)) -> ERICK HYLARIO | C40: =VLOOKUP(TRIM(Tabela2[[#This Row],[SEI]]),Tabela3[[Processo SEI]:[Objeto]],5,FALSE) -> CONCLUSÃO DAS OBRAS DO MUSEU DA IMAGEM E DO SOM - COPACABANA - RJ | D40: MPE | E40: RIO DE JANEIRO | G40: DISTRATO | H40: ESPECIAIS | I40: =IFERROR(VLOOKUP(TRIM(Tabela2[[#This Row],[SEI]]),[1]Medições!$B$2:$H$48,7,FALSE),Tabela2[[#This Row],[STATUS_original]]) -> DISTRATO
A41: 170026/001757/2021 | B41: =IFERROR(VLOOKUP(TRIM(A41),[1]Medições!$B$2:$I$48,8,FALSE),VLOOKUP(TRIM(A41),[1]PROBLEMAS!$B$2:$I$122,8,FALSE)) -> ERICK HYLARIO | C41: =VLOOKUP(TRIM(Tabela2[[#This Row],[SEI]]),Tabela3[[Processo SEI]:[Objeto]],5,FALSE) -> OBRAS DE ILUMINAÇÃO E ACABAMENTOS - MUSEU DA IMAGEM E DO SOM - COPACABANA - RJ | D41: MPE | E41: RIO DE JANEIRO | G41: DISTRATO | H41: ESPECIAIS | I41: =IFERROR(VLOOKUP(TRIM(Tabela2[[#This Row],[SEI]]),[1]Medições!$B$2:$H$48,7,FALSE),Tabela2[[#This Row],[STATUS_original]]) -> DISTRATO
A42: 170026/003470/2021 | B42: =IFERROR(VLOOKUP(TRIM(A42),[1]Medições!$B$2:$I$48,8,FALSE),VLOOKUP(TRIM(A42),[1]PROBLEMAS!$B$2:$I$122,8,FALSE)) -> ERICK HYLARIO | C42: =VLOOKUP(TRIM(Tabela2[[#This Row],[SEI]]),Tabela3[[Processo SEI]:[Objeto]],5,FALSE) -> RECUPERAÇÃO DAS ESTAÇÕES DO TELEFÉRICO DO ALEMÃO – RJ | D42: PETROPUMP | E42: RIO DE JANEIRO | F42: HIGOR MARTINS / DANRLEI GOMES | G42: ACEITE PROVISORIO | H42: ESPECIAIS | I42: =IFERROR(VLOOKUP(TRIM(Tabela2[[#This Row],[SEI]]),[1]Medições!$B$2:$H$48,7,FALSE),Tabela2[[#This Row],[STATUS_original]]) -> ACEITE PROVISORIO
A43: 170026/000214/2022 | B43: =IFERROR(VLOOKUP(TRIM(A43),[1]Medições!$B$2:$I$48,8,FALSE),VLOOKUP(TRIM(A43),[1]PROBLEMAS!$B$2:$I$122,8,FALSE)) -> ERICK HYLARIO | C43: =VLOOKUP(TRIM(Tabela2[[#This Row],[SEI]]),Tabela3[[Processo SEI]:[Objeto]],5,FALSE) -> AQUISIÇÃO DE EQUIPAMENTOS PARA TELEFÉRICO DO ALEMÃO – RJ | D43: POMA | E43: RIO DE JANEIRO | G43: EXECUÇÃO | H43: ESPECIAIS | I43: =IFERROR(VLOOKUP(TRIM(Tabela2[[#This Row],[SEI]]),[1]Medições!$B$2:$H$48,7,FALSE),Tabela2[[#This Row],[STATUS_original]]) -> EXECUÇÃO
A44: 330018/000190/2022 | B44: =IFERROR(VLOOKUP(TRIM(A44),[1]Medições!$B$2:$I$48,8,FALSE),VLOOKUP(TRIM(A44),[1]PROBLEMAS!$B$2:$I$122,8,FALSE)) -> GISELLE G. FONSECA | C44: =VLOOKUP(TRIM(Tabela2[[#This Row],[SEI]]),Tabela3[[Processo SEI]:[Objeto]],5,FALSE) -> MACRODRENAGEM DO CANAL VILA CANAAN - DUQUE DE CAXIAS | D44: BRASFORM | E44: DUQUE DE CAXIAS | F44: CAIO / LUIZ FILHO | G44: CONCLUIDA | H44: BX | I44: =IFERROR(VLOOKUP(TRIM(Tabela2[[#This Row],[SEI]]),[1]Medições!$B$2:$H$48,7,FALSE),Tabela2[[#This Row],[STATUS_original]]) -> CONCLUIDA
A45: 170026/002777/2021 | B45: =IFERROR(VLOOKUP(TRIM(A45),[1]Medições!$B$2:$I$48,8,FALSE),VLOOKUP(TRIM(A45),[1]PROBLEMAS!$B$2:$I$122,8,FALSE)) -> GISELLE G. FONSECA | C45: =VLOOKUP(TRIM(Tabela2[[#This Row],[SEI]]),Tabela3[[Processo SEI]:[Objeto]],5,FALSE) -> PROJETO EXECUTIVO E EXECUÇÃO DE OBRAS DE DRENAGEM, PAVIMENTAÇÃO E INFRAESTRUTURA – SÃO JOSÉ – JAPERI/RJ | D45: CONS. SÃO JOSÉ - HY./ MED. | E45: JAPERI | F45: OSVALDO NETO | G45: DISTRATO | H45: BX | I45: =IFERROR(VLOOKUP(TRIM(Tabela2[[#This Row],[SEI]]),[1]Medições!$B$2:$H$48,7,FALSE),Tabela2[[#This Row],[STATUS_original]]) -> DISTRATO
A46: 170026/001611/2020 | B46: =IFERROR(VLOOKUP(TRIM(A46),[1]Medições!$B$2:$I$48,8,FALSE),VLOOKUP(TRIM(A46),[1]PROBLEMAS!$B$2:$I$122,8,FALSE)) -> GISELLE G. FONSECA | C46: =VLOOKUP(TRIM(Tabela2[[#This Row],[SEI]]),Tabela3[[Processo SEI]:[Objeto]],5,FALSE) -> REVITALIZAÇÃO DA CICLOVIA E CALÇADA DA ORLA DA PRAIA DO SACO - MANGARATIBA/RJ | D46: GONÇALVES NEVES | E46: MANGARATIBA | F46: OSVALDO NETO | G46: CONCLUIDA | H46: BX | I46: =IFERROR(VLOOKUP(TRIM(Tabela2[[#This Row],[SEI]]),[1]Medições!$B$2:$H$48,7,FALSE),Tabela2[[#This Row],[STATUS_original]]) -> CONCLUIDA
A47: 330018/001315/2022 | B47: =IFERROR(VLOOKUP(TRIM(A47),[1]Medições!$B$2:$I$48,8,FALSE),VLOOKUP(TRIM(A47),[1]PROBLEMAS!$B$2:$I$122,8,FALSE)) -> GISELLE G. FONSECA | C47: =VLOOKUP(TRIM(Tabela2[[#This Row],[SEI]]),Tabela3[[Processo SEI]:[Objeto]],5,FALSE) -> IMPLANTAÇÃO DE CICLOVIA E CALÇADA NA ESTRADA ZUMBI – NOVA IGUAÇU/RJ | D47: HYDRA | E47: NOVA IGUAÇÚ | F47: MAURÍCIO | G47: DISTRATO | H47: BX | I47: =IFERROR(VLOOKUP(TRIM(Tabela2[[#This Row],[SEI]]),[1]Medições!$B$2:$H$48,7,FALSE),Tabela2[[#This Row],[STATUS_original]]) -> DISTRATO
A48: 330018/001076/2021 | B48: =IFERROR(VLOOKUP(TRIM(A48),[1]Medições!$B$2:$I$48,8,FALSE),VLOOKUP(TRIM(A48),[1]PROBLEMAS!$B$2:$I$122,8,FALSE)) -> GISELLE G. FONSECA | C48: =VLOOKUP(TRIM(Tabela2[[#This Row],[SEI]]),Tabela3[[Processo SEI]:[Objeto]],5,FALSE) -> MACRODRENAGEM DO CANAL VASQUINHO – DUQUE DE CAXIAS/RJ | D48: HYDRA | E48: DUQUE DE CAXIAS | F48: LUCIANA POSTIÇO / ARLINDO BASILIO | G48: CONCLUIDA | H48: BX | I48: =IFERROR(VLOOKUP(TRIM(Tabela2[[#This Row],[SEI]]),[1]Medições!$B$2:$H$48,7,FALSE),Tabela2[[#This Row],[STATUS_original]]) -> CONCLUIDA
A49: 170026/000122/2022 | B49: =IFERROR(VLOOKUP(TRIM(A49),[1]Medições!$B$2:$I$48,8,FALSE),VLOOKUP(TRIM(A49),[1]PROBLEMAS!$B$2:$I$122,8,FALSE)) -> GISELLE G. FONSECA | C49: =VLOOKUP(TRIM(Tabela2[[#This Row],[SEI]]),Tabela3[[Processo SEI]:[Objeto]],5,FALSE) -> PAVIMENTAÇÃO, DRENAGEM E PONTE NA ESTRADA TIRADENTES – PARAÍBA DO SUL/RJ | D49: HJ RODRIGUES | E49: PARAÍBA DO SUL | F49: NICHOLAS TAVARES / MAURÍCIO | G49: CONCLUIDA | H49: BX | I49: =IFERROR(VLOOKUP(TRIM(Tabela2[[#This Row],[SEI]]),[1]Medições!$B$2:$H$48,7,FALSE),Tabela2[[#This Row],[STATUS_original]]) -> CONCLUIDA
A50: 170026/001549/2020 | B50: =IFERROR(VLOOKUP(TRIM(A50),[1]Medições!$B$2:$I$48,8,FALSE),VLOOKUP(TRIM(A50),[1]PROBLEMAS!$B$2:$I$122,8,FALSE)) -> GISELLE G. FONSECA | C50: =VLOOKUP(TRIM(Tabela2[[#This Row],[SEI]]),Tabela3[[Processo SEI]:[Objeto]],5,FALSE) -> REVITALIZAÇÃO DAS PRAÇAS CURUPAITI, BREJAL E BELA VISTA - PARAÍBA DO SUL/RJ | D50: ABBM | E50: PARAÍBA DO SUL | F50: NICHOLAS TAVARES / MAURÍCIO | G50: CONCLUIDA | H50: BX | I50: =IFERROR(VLOOKUP(TRIM(Tabela2[[#This Row],[SEI]]),[1]Medições!$B$2:$H$48,7,FALSE),Tabela2[[#This Row],[STATUS_original]]) -> CONCLUIDA
A51: 170026/000318/2022 | B51: =IFERROR(VLOOKUP(TRIM(A51),[1]Medições!$B$2:$I$48,8,FALSE),VLOOKUP(TRIM(A51),[1]PROBLEMAS!$B$2:$I$122,8,FALSE)) -> GISELLE G. FONSECA | C51: =VLOOKUP(TRIM(Tabela2[[#This Row],[SEI]]),Tabela3[[Processo SEI]:[Objeto]],5,FALSE) -> CANALIZAÇÃO DO CANAL DO LEITÃO - MANGARATIBA/RJ | D51: LYTORANEA | E51: MANGARATIBA | F51: ARLINDO BASILIO / OTAVIO FEITOSA | G51: SUSPENSA | H51: BX | I51: =IFERROR(VLOOKUP(TRIM(Tabela2[[#This Row],[SEI]]),[1]Medições!$B$2:$H$48,7,FALSE),Tabela2[[#This Row],[STATUS_original]]) -> SUSPENSA
A52: 330018/001363/2022 | B52: =IFERROR(VLOOKUP(TRIM(A52),[1]Medições!$B$2:$I$48,8,FALSE),VLOOKUP(TRIM(A52),[1]PROBLEMAS!$B$2:$I$122,8,FALSE)) -> GISELLE G. FONSECA | C52: =VLOOKUP(TRIM(Tabela2[[#This Row],[SEI]]),Tabela3[[Processo SEI]:[Objeto]],5,FALSE) -> RECUPERAÇÃO DE PAVIMENTAÇÃO E SINALIZAÇÃO EM DUQUE DE CAXIAS | D52: MJRE | E52: DUQUE DE CAXIAS | F52: LUCIANA POSTIÇO / OSVALDO NETO | G52: ACEITE PROVISORIO | H52: BX | I52: =IFERROR(VLOOKUP(TRIM(Tabela2[[#This Row],[SEI]]),[1]Medições!$B$2:$H$48,7,FALSE),Tabela2[[#This Row],[STATUS_original]]) -> ACEITE PROVISORIO
A53: 330018/001141/2022 | B53: =IFERROR(VLOOKUP(TRIM(A53),[1]Medições!$B$2:$I$48,8,FALSE),VLOOKUP(TRIM(A53),[1]PROBLEMAS!$B$2:$I$122,8,FALSE)) -> GISELLE G. FONSECA | C53: =VLOOKUP(TRIM(Tabela2[[#This Row],[SEI]]),Tabela3[[Processo SEI]:[Objeto]],5,FALSE) -> DRENAGEM PLUVIAL E PAVIMENTAÇÃO NO BAIRRO VALDARIOSA – QUEIMADOS/RJ | D53: LYTORANEA | E53: QUEIMADOS | F53: LUCIANA POSTIÇO / NICHOLAS TAVARES | G53: ACEITE PROVISORIO | H53: BX | I53: =IFERROR(VLOOKUP(TRIM(Tabela2[[#This Row],[SEI]]),[1]Medições!$B$2:$H$48,7,FALSE),Tabela2[[#This Row],[STATUS_original]]) -> ACEITE PROVISORIO
A54: 330018/000730/2021 | B54: =IFERROR(VLOOKUP(TRIM(A54),[1]Medições!$B$2:$I$48,8,FALSE),VLOOKUP(TRIM(A54),[1]PROBLEMAS!$B$2:$I$122,8,FALSE)) -> GISELLE G. FONSECA | C54: =VLOOKUP(TRIM(Tabela2[[#This Row],[SEI]]),Tabela3[[Processo SEI]:[Objeto]],5,FALSE) -> URBANIZAÇÃO DAS ÁREAS LINDEIRAS AO RIO CAMORIM – QUEIMADOS/RJ | D54: MONJARDIN | E54: QUEIMADOS | F54: LUCIANA POSTIÇO / NICHOLAS TAVARES | G54: ACEITE DEFINITIVO | H54: BX | I54: =IFERROR(VLOOKUP(TRIM(Tabela2[[#This Row],[SEI]]),[1]Medições!$B$2:$H$48,7,FALSE),Tabela2[[#This Row],[STATUS_original]]) -> ACEITE DEFINITIVO
A55: 170026/001967/2021 | B55: =IFERROR(VLOOKUP(TRIM(A55),[1]Medições!$B$2:$I$48,8,FALSE),VLOOKUP(TRIM(A55),[1]PROBLEMAS!$B$2:$I$122,8,FALSE)) -> GISELLE G. FONSECA | C55: =VLOOKUP(TRIM(Tabela2[[#This Row],[SEI]]),Tabela3[[Processo SEI]:[Objeto]],5,FALSE) -> PAVIMENTAÇÃO E DRENAGEM – ESTRADA RIO DAS PEDRAS – RIO CLARO-RJ | D55: NF | E55: RIO CLARO | F55: NICHOLAS TAVARES | G55: DISTRATO | H55: BX | I55: =IFERROR(VLOOKUP(TRIM(Tabela2[[#This Row],[SEI]]),[1]Medições!$B$2:$H$48,7,FALSE),Tabela2[[#This Row],[STATUS_original]]) -> DISTRATO
... A81: 330001/001337/2025 | B81: =IFERROR(VLOOKUP(TRIM(A81),[1]Medições!$B$2:$I$48,8,FALSE),VLOOKUP(TRIM(A81),[1]PROBLEMAS!$B$2:$I$122,8,FALSE)) -> GISELLE G. FONSECA | C81: =VLOOKUP(TRIM(Tabela2[[#This Row],[SEI]]),Tabela3[[Processo SEI]:[Objeto]],5,FALSE) -> STABILIZAÇÃO DE TALUDES NA RUA URUGUAI NO BAIRRO QUITANDINHA-PETROPOLIS | D81: DRV | E81: PETROPOLIS | F81: ARLINDO BASILIO / NICHOLAS TAVARES | G81: EXECUÇÃO | H81: CONT | I81: =IFERROR(VLOOKUP(TRIM(Tabela2[[#This Row],[SEI]]),[1]Medições!$B$2:$H$48,7,FALSE),Tabela2[[#This Row],[STATUS_original]]) -> EXECUÇÃO
A82: 330018/000566/2021 | B82: =IFERROR(VLOOKUP(TRIM(A82),[1]Medições!$B$2:$I$48,8,FALSE),VLOOKUP(TRIM(A82),[1]PROBLEMAS!$B$2:$I$122,8,FALSE)) -> GISELLE G. FONSECA | C82: =VLOOKUP(TRIM(Tabela2[[#This Row],[SEI]]),Tabela3[[Processo SEI]:[Objeto]],5,FALSE) -> DRENAGEM E PAVIMENTAÇÃO NO JARDIM DELAMARE, JAPERI/RJ | D82: OMEGA | E82: JAPERI | G82: ACEITE DEFINITIVO | H82: ESPECIAIS | I82: =IFERROR(VLOOKUP(TRIM(Tabela2[[#This Row],[SEI]]),[1]Medições!$B$2:$H$48,7,FALSE),Tabela2[[#This Row],[STATUS_original]]) -> ACEITE DEFINITIVO
A83: 170026/000821/2021 | B83: =IFERROR(VLOOKUP(TRIM(A83),[1]Medições!$B$2:$I$48,8,FALSE),VLOOKUP(TRIM(A83),[1]PROBLEMAS!$B$2:$I$122,8,FALSE)) -> IGOR CARNEIRO | C83: =VLOOKUP(TRIM(Tabela2[[#This Row],[SEI]]),Tabela3[[Processo SEI]:[Objeto]],5,FALSE) -> CONSTRUÇÃO DO COE E DE EQUIPAMENTO MODULAR – RIO DE JANEIRO | D83: CARLETTI | E83: RIO DE JANEIRO | F83: OSVALDO NETO / HIGOR MARTINS | G83: #CONCLUIDA | H83: ESPECIAIS | I83: =IFERROR(VLOOKUP(TRIM(Tabela2[[#This Row],[SEI]]),[1]Medições!$B$2:$H$48,7,FALSE),Tabela2[[#This Row],[STATUS_original]]) -> #CONCLUIDA
A84: 170026/000277/2021 | B84: =IFERROR(VLOOKUP(TRIM(A84),[1]Medições!$B$2:$I$48,8,FALSE),VLOOKUP(TRIM(A84),[1]PROBLEMAS!$B$2:$I$122,8,FALSE)) -> IGOR CARNEIRO | C84: =VLOOKUP(TRIM(Tabela2[[#This Row],[SEI]]),Tabela3[[Processo SEI]:[Objeto]],5,FALSE) -> CONSTRUÇÃO DO COLÉGIO ESTADUAL LUIZ MELODIA – RIO DE JANEIRO | D84: CARLETTI | E84: RIO DE JANEIRO | F84: HIGOR MARTINS / IZADORA COE | G84: EXECUÇÃO | H84: ESPECIAIS | I84: =IFERROR(VLOOKUP(TRIM(Tabela2[[#This Row],[SEI]]),[1]Medições!$B$2:$H$48,7,FALSE),Tabela2[[#This Row],[STATUS_original]]) -> EXECUÇÃO
A85: 180007/000770/2022 | B85: =IFERROR(VLOOKUP(TRIM(A85),[1]Medições!$B$2:$I$48,8,FALSE),VLOOKUP(TRIM(A85),[1]PROBLEMAS!$B$2:$I$122,8,FALSE)) -> IGOR CARNEIRO | C85: =VLOOKUP(TRIM(Tabela2[[#This Row],[SEI]]),Tabela3[[Processo SEI]:[Objeto]],5,FALSE) -> OBRAS DE RESTAURAÇÃO NO PALACETE DO PARQUE LAGE – RJ | D85: CONSTRUPOWER | E85: RIO DE JANEIRO | F85: HIGOR MARTINS / DANRLEI GOMES | G85: EXECUÇÃO | H85: ESPECIAIS | I85: =IFERROR(VLOOKUP(TRIM(Tabela2[[#This Row],[SEI]]),[1]Medições!$B$2:$H$48,7,FALSE),Tabela2[[#This Row],[STATUS_original]]) -> EXECUÇÃO
A86: 460001/000416/2023 | B86: =IFERROR(VLOOKUP(TRIM(A86),[1]Medições!$B$2:$I$48,8,FALSE),VLOOKUP(TRIM(A86),[1]PROBLEMAS!$B$2:$I$122,8,FALSE)) -> IGOR CARNEIRO | C86: =VLOOKUP(TRIM(Tabela2[[#This Row],[SEI]]),Tabela3[[Processo SEI]:[Objeto]],5,FALSE) -> IMPLANTAÇÃO DA PONTE DO PILAR E INFRAESTRUTURA – DUQUE DE CAXIAS/RJ | D86: ÔMEGA | E86: DUQUE DE CAXIAS | F86: HIGOR MARTINS / IZADORA COE | G86: EXECUÇÃO | H86: ESPECIAIS | I86: =IFERROR(VLOOKUP(TRIM(Tabela2[[#This Row],[SEI]]),[1]Medições!$B$2:$H$48,7,FALSE),Tabela2[[#This Row],[STATUS_original]]) -> EXECUÇÃO
A87: 330018/000619/2021 | B87: =IFERROR(VLOOKUP(TRIM(A87),[1]Medições!$B$2:$I$48,8,FALSE),VLOOKUP(TRIM(A87),[1]PROBLEMAS!$B$2:$I$122,8,FALSE)) -> ISADORA ROSALINO | C87: =VLOOKUP(TRIM(Tabela2[[#This Row],[SEI]]),Tabela3[[Processo SEI]:[Objeto]],5,FALSE) -> PAVIMENTAÇÃO, URBANIZAÇÃO E DRENAGEM EM PARQUE SARAIVA - CAMPOS | D87: PARQUE SARAIVA | E87: CAMPOS | F87: JEHNIFFER PIRES / ANDREIA VASQUES | G87: #CONCLUIDA | H87: NT | I87: =IFERROR(VLOOKUP(TRIM(Tabela2[[#This Row],[SEI]]),[1]Medições!$B$2:$H$48,7,FALSE),Tabela2[[#This Row],[STATUS_original]]) -> #CONCLUIDA
A88: 330018/000694/2021 | B88: =IFERROR(VLOOKUP(TRIM(A88),[1]Medições!$B$2:$I$48,8,FALSE),VLOOKUP(TRIM(A88),[1]PROBLEMAS!$B$2:$I$122,8,FALSE)) -> ISADORA ROSALINO | C88: =VLOOKUP(TRIM(Tabela2[[#This Row],[SEI]]),Tabela3[[Processo SEI]:[Objeto]],5,FALSE) -> PAVIMENTAÇÃO, URBANIZAÇÃO E DRENAGEM NOS BAIRROS DE CAMPOS | D88: IMBEG | E88: CAMPOS | F88: JEHNIFFER PIRES / ANDREIA VASQUES | G88: EXECUÇÃO | H88: NT | I88: =IFERROR(VLOOKUP(TRIM(Tabela2[[#This Row],[SEI]]),[1]Medições!$B$2:$H$48,7,FALSE),Tabela2[[#This Row],[STATUS_original]]) -> EXECUÇÃO
A89: 330018/000695/2021 | B89: =IFERROR(VLOOKUP(TRIM(A89),[1]Medições!$B$2:$I$48,8,FALSE),VLOOKUP(TRIM(A89),[1]PROBLEMAS!$B$2:$I$122,8,FALSE)) -> ISADORA ROSALINO | C89: =VLOOKUP(TRIM(Tabela2[[#This Row],[SEI]]),Tabela3[[Processo SEI]:[Objeto]],5,FALSE) -> REVESTIMENTO ASFÁLTICO E DRENAGEM EM PORTO BELO –EM CAMPOS/RJ | D89: ACA | E89: CAMPOS | F89: JEHNIFFER PIRES / ANDREIA VASQUES | G89: EXECUÇÃO | H89: NT | I89: =IFERROR(VLOOKUP(TRIM(Tabela2[[#This Row],[SEI]]),[1]Medições!$B$2:$H$48,7,FALSE),Tabela2[[#This Row],[STATUS_original]]) -> EXECUÇÃO
A90: 330018/000696/2021 | B90: =IFERROR(VLOOKUP(TRIM(A90),[1]Medições!$B$2:$I$48,8,FALSE),VLOOKUP(TRIM(A90),[1]PROBLEMAS!$B$2:$I$122,8,FALSE)) -> ISADORA ROSALINO | C90: =VLOOKUP(TRIM(Tabela2[[#This Row],[SEI]]),Tabela3[[Processo SEI]:[Objeto]],5,FALSE) -> REVESTIMENTO ASFÁLTICO E DRENAGEM NOS BAIRROS DE CAMPOS | D90: NOVO MUNDO | E90: CAMPOS | F90: JEHNIFFER PIRES / ANDREIA VASQUES | G90: EXECUÇÃO | H90: NT | I90: =IFERROR(VLOOKUP(TRIM(Tabela2[[#This Row],[SEI]]),[1]Medições!$B$2:$H$48,7,FALSE),Tabela2[[#This Row],[STATUS_original]]) -> EXECUÇÃO
A91: 170026/001792/2021 | B91: =IFERROR(VLOOKUP(TRIM(A91),[1]Medições!$B$2:$I$48,8,FALSE),VLOOKUP(TRIM(A91),[1]PROBLEMAS!$B$2:$I$122,8,FALSE)) -> ISADORA ROSALINO | C91: =VLOOKUP(TRIM(Tabela2[[#This Row],[SEI]]),Tabela3[[Processo SEI]:[Objeto]],5,FALSE) -> TERMINAL RODOVIÁRIO – TERESÓPOLIS | D91: JKN | E91: TERESOPOLIS | F91: LUCIANA POSTIÇO / NICHOLAS TAVARES | G91: ACEITE PROVISORIO | H91: NT | I91: =IFERROR(VLOOKUP(TRIM(Tabela2[[#This Row],[SEI]]),[1]Medições!$B$2:$H$48,7,FALSE),Tabela2[[#This Row],[STATUS_original]]) -> ACEITE PROVISORIO
A92: 170026/003264/2021 | B92: =IFERROR(VLOOKUP(TRIM(A92),[1]Medições!$B$2:$I$48,8,FALSE),VLOOKUP(TRIM(A92),[1]PROBLEMAS!$B$2:$I$122,8,FALSE)) -> ISADORA ROSALINO | C92: =VLOOKUP(TRIM(Tabela2[[#This Row],[SEI]]),Tabela3[[Processo SEI]:[Objeto]],5,FALSE) -> CONSTRUÇÃO DE ACOSTAMENTO, CICLOVIA E CALÇADA EM PRAIA SECA – ARARUAMA/RJ | D92: OMEGA | E92: ARARUAMA | F92: LIVIA ALVIM | G92: CONCLUIDA | H92: NT | I92: =IFERROR(VLOOKUP(TRIM(Tabela2[[#This Row],[SEI]]),[1]Medições!$B$2:$H$48,7,FALSE),Tabela2[[#This Row],[STATUS_original]]) -> CONCLUIDA
A93: 170026/002183/2021 | B93: =IFERROR(VLOOKUP(TRIM(A93),[1]Medições!$B$2:$I$48,8,FALSE),VLOOKUP(TRIM(A93),[1]PROBLEMAS!$B$2:$I$122,8,FALSE)) -> ISADORA ROSALINO | C93: =VLOOKUP(TRIM(Tabela2[[#This Row],[SEI]]),Tabela3[[Processo SEI]:[Objeto]],5,FALSE) -> ADAPTAÇÃO DE PONTE FERROVIÁRIA PARA PISTA E CICLOVIA - CARDOSO MOREIRA/RJ | D93: R.C. VIEIRA | E93: CARDOSO DE MORAES | F93: LIVIA ALVIM | G93: CONCLUIDA | H93: NT | I93: =IFERROR(VLOOKUP(TRIM(Tabela2[[#This Row],[SEI]]),[1]Medições!$B$2:$H$48,7,FALSE),Tabela2[[#This Row],[STATUS_original]]) -> CONCLUIDA
A94: 170026/001772/2022 | B94: =IFERROR(VLOOKUP(TRIM(A94),[1]Medições!$B$2:$I$48,8,FALSE),VLOOKUP(TRIM(A94),[1]PROBLEMAS!$B$2:$I$122,8,FALSE)) -> ISADORA ROSALINO | C94: =VLOOKUP(TRIM(Tabela2[[#This Row],[SEI]]),Tabela3[[Processo SEI]:[Objeto]],5,FALSE) -> PROJETOS EXECUTIVOS E REFORMA DAS ÁREAS ESPORTIVAS EM CONCEIÇÃO DE MACABU | D94: PETROPUMP | E94: CONCEIÇÃO DE MACABU | F94: JEHNIFFER PIRES / ANDREIA VASQUES | G94: EXECUÇÃO | H94: NT | I94: =IFERROR(VLOOKUP(TRIM(Tabela2[[#This Row],[SEI]]),[1]Medições!$B$2:$H$48,7,FALSE),Tabela2[[#This Row],[STATUS_original]]) -> EXECUÇÃO
... A112: 330001/001080/2025 | B112: =IFERROR(VLOOKUP(TRIM(A112),[1]Medições!$B$2:$I$48,8,FALSE),VLOOKUP(TRIM(A112),[1]PROBLEMAS!$B$2:$I$122,8,FALSE)) -> JAQUELINE PASTÓRIO | C112: =VLOOKUP(TRIM(Tabela2[[#This Row],[SEI]]),Tabela3[[Processo SEI]:[Objeto]],5,FALSE) -> REVESTIMENTO ASFÁLTICO, DRENAGEM, CONSTRUÇÃO DE GALERIAS DE ÁGUAS PLUVIAIS, URBANIZAÇÃO, CICLOFAIXA E ESTABILIZAÇÃO DE TALUDE, MUNICÍPIO DE BARRA DO PIRAÍ - RJJ | D112: AXIAL | E112: BARRA DO PIRAÍ | F112: LUCIANA POSTIÇO / LEANDRO RAMOS | G112: EXECUÇÃO | H112: SL | I112: =IFERROR(VLOOKUP(TRIM(Tabela2[[#This Row],[SEI]]),[1]Medições!$B$2:$H$48,7,FALSE),Tabela2[[#This Row],[STATUS_original]]) -> EXECUÇÃO
A113: 170026/001374/2022 | B113: =IFERROR(VLOOKUP(TRIM(A113),[1]Medições!$B$2:$I$48,8,FALSE),VLOOKUP(TRIM(A113),[1]PROBLEMAS!$B$2:$I$122,8,FALSE)) -> JAQUELINE PASTÓRIO | C113: =VLOOKUP(TRIM(Tabela2[[#This Row],[SEI]]),Tabela3[[Processo SEI]:[Objeto]],5,FALSE) -> CONTENÇÃO E DRENAGEM - ILHA DO ARROZ, ANGRA DOS REIS/RJ | D113: BARRA NOVA | E113: ANGRA DOS REIS | G113: CONCLUIDA | H113: ESPECIAIS | I113: =IFERROR(VLOOKUP(TRIM(Tabela2[[#This Row],[SEI]]),[1]Medições!$B$2:$H$48,7,FALSE),Tabela2[[#This Row],[STATUS_original]]) -> CONCLUIDA
A114: 170026/001228/2022 | B114: =IFERROR(VLOOKUP(TRIM(A114),[1]Medições!$B$2:$I$48,8,FALSE),VLOOKUP(TRIM(A114),[1]PROBLEMAS!$B$2:$I$122,8,FALSE)) -> JAQUELINE PASTÓRIO | C114: =VLOOKUP(TRIM(Tabela2[[#This Row],[SEI]]),Tabela3[[Processo SEI]:[Objeto]],5,FALSE) -> ESTABILIZAÇÃO DE TALUDE - VILA MURIQUI, MANGARATIBA/RJ | D114: DRV | E114: MANGARATIBA | G114: CONCLUIDA | H114: ESPECIAIS | I114: =IFERROR(VLOOKUP(TRIM(Tabela2[[#This Row],[SEI]]),[1]Medições!$B$2:$H$48,7,FALSE),Tabela2[[#This Row],[STATUS_original]]) -> CONCLUIDA
A115: 460001/000251/2023 | B115: =IFERROR(VLOOKUP(TRIM(A115),[1]Medições!$B$2:$I$48,8,FALSE),VLOOKUP(TRIM(A115),[1]PROBLEMAS!$B$2:$I$122,8,FALSE)) -> JAQUELINE PASTÓRIO | C115: =VLOOKUP(TRIM(Tabela2[[#This Row],[SEI]]),Tabela3[[Processo SEI]:[Objeto]],5,FALSE) -> RECOMPOSIÇÃO DO DIQUE E MARGEM DO RIO PARAÍBA DO SUL - CAMPOS DOS GOYTACAZES/RJ | D115: DRV ENGENHARIA | E115: CAMPOS DOS GOYTACAZES | G115: CONCLUIDA | H115: ESPECIAIS | I115: =IFERROR(VLOOKUP(TRIM(Tabela2[[#This Row],[SEI]]),[1]Medições!$B$2:$H$48,7,FALSE),Tabela2[[#This Row],[STATUS_original]]) -> CONCLUIDA
A116: E-17/026/903/2019 | B116: =IFERROR(VLOOKUP(TRIM(A116),[1]Medições!$B$2:$I$48,8,FALSE),VLOOKUP(TRIM(A116),[1]PROBLEMAS!$B$2:$I$122,8,FALSE)) -> JAQUELINE PASTÓRIO | C116: =VLOOKUP(TRIM(Tabela2[[#This Row],[SEI]]),Tabela3[[Processo SEI]:[Objeto]],5,FALSE) -> CONSTRUÇÃO DE EQUIPAMENTO MODULAR PARA O COLÉGIO ZILDA ARNS - GUARATIBA - RJ | D116: ENGEPRAT | E116: RIO DE JANEIRO | G116: DISTRATO | H116: ESPECIAIS | I116: =IFERROR(VLOOKUP(TRIM(Tabela2[[#This Row],[SEI]]),[1]Medições!$B$2:$H$48,7,FALSE),Tabela2[[#This Row],[STATUS_original]]) -> DISTRATO
A117: 330018/000981/2021 | B117: =IFERROR(VLOOKUP(TRIM(A117),[1]Medições!$B$2:$I$48,8,FALSE),VLOOKUP(TRIM(A117),[1]PROBLEMAS!$B$2:$I$122,8,FALSE)) -> JAQUELINE PASTÓRIO | C117: =VLOOKUP(TRIM(Tabela2[[#This Row],[SEI]]),Tabela3[[Processo SEI]:[Objeto]],5,FALSE) -> PAVIMENTAÇÃO E DRENAGEM EM CENTRO DE NOVA FRIBURGO | D117: ÔMEGA | E117: NOVA FRIBURGO | G117: CONCLUIDA | H117: ESPECIAIS | I117: =IFERROR(VLOOKUP(TRIM(Tabela2[[#This Row],[SEI]]),[1]Medições!$B$2:$H$48,7,FALSE),Tabela2[[#This Row],[STATUS_original]]) -> CONCLUIDA
A118: 170026/001837/2022 | B118: =IFERROR(VLOOKUP(TRIM(A118),[1]Medições!$B$2:$I$48,8,FALSE),VLOOKUP(TRIM(A118),[1]PROBLEMAS!$B$2:$I$122,8,FALSE)) -> JEHNIFFER PIRES | C118: =VLOOKUP(TRIM(Tabela2[[#This Row],[SEI]]),Tabela3[[Processo SEI]:[Objeto]],5,FALSE) -> CONSTRUÇÃO DO CENTRO DE CONVENÇÕES JACKSON UCHOA VIANNA – MIGUEL PEREIRA/RJ | D118: PETROPUMP | E118: MIGUEL PEREIRA | F118: LUCIANA POSTIÇO / ARLINDO BASILIO | G118: #CONCLUIDA | H118: BX | I118: =IFERROR(VLOOKUP(TRIM(Tabela2[[#This Row],[SEI]]),[1]Medições!$B$2:$H$48,7,FALSE),Tabela2[[#This Row],[STATUS_original]]) -> #CONCLUIDA
A119: 170026/002043/2021 | B119: =IFERROR(VLOOKUP(TRIM(A119),[1]Medições!$B$2:$I$48,8,FALSE),VLOOKUP(TRIM(A119),[1]PROBLEMAS!$B$2:$I$122,8,FALSE)) -> JEHNIFFER PIRES | C119: =VLOOKUP(TRIM(Tabela2[[#This Row],[SEI]]),Tabela3[[Processo SEI]:[Objeto]],5,FALSE) -> PROJETOS EXECUTIVOS E RECAPEAMENTO VIÁRIO EM CAMPOS | D119: METROPOLITANA | E119: CAMPOS | F119: LIVIA ALVIM / ANDREIA VASQUES | G119: DISTRATO | H119: NT | I119: =IFERROR(VLOOKUP(TRIM(Tabela2[[#This Row],[SEI]]),[1]Medições!$B$2:$H$48,7,FALSE),Tabela2[[#This Row],[STATUS_original]]) -> DISTRATO
A120: 330018/000156/2022 | B120: =IFERROR(VLOOKUP(TRIM(A120),[1]Medições!$B$2:$I$48,8,FALSE),VLOOKUP(TRIM(A120),[1]PROBLEMAS!$B$2:$I$122,8,FALSE)) -> JEHNIFFER PIRES | C120: =VLOOKUP(TRIM(Tabela2[[#This Row],[SEI]]),Tabela3[[Processo SEI]:[Objeto]],5,FALSE) -> PAVIMENTAÇÃO, ÁGUA, ESGOTO E DRENAGEM EM FAROL DE SÃO THOMÉ - CAMPOS | D120: VILA DOS PESCADORES | E120: CAMPOS | F120: ISADORA ROSALINO / ANDREIA VASQUES | G120: #CONCLUIDA | H120: NT | I120: =IFERROR(VLOOKUP(TRIM(Tabela2[[#This Row],[SEI]]),[1]Medições!$B$2:$H$48,7,FALSE),Tabela2[[#This Row],[STATUS_original]]) -> #CONCLUIDA
A121: 460001/001990/2023 | B121: =IFERROR(VLOOKUP(TRIM(A121),[1]Medições!$B$2:$I$48,8,FALSE),VLOOKUP(TRIM(A121),[1]PROBLEMAS!$B$2:$I$122,8,FALSE)) -> JEHNIFFER PIRES | C121: =VLOOKUP(TRIM(Tabela2[[#This Row],[SEI]]),Tabela3[[Processo SEI]:[Objeto]],5,FALSE) -> CONSTRUÇÃO DO COMPLEXO URBANÍSTICO CARDOSO MOREIRA – RJ | D121: PREST RIO CONSTRUÇÕES E SERVIÇOS Ltda | E121: CARDOSO MOREIRA | F121: ANDREIA VASQUES / ISADORA ROSALINO | G121: EXECUÇÃO | H121: NT | I121: =IFERROR(VLOOKUP(TRIM(Tabela2[[#This Row],[SEI]]),[1]Medições!$B$2:$H$48,7,FALSE),Tabela2[[#This Row],[STATUS_original]]) -> EXECUÇÃO
A122: 330018/000085/2022 | B122: =IFERROR(VLOOKUP(TRIM(A122),[1]Medições!$B$2:$I$48,8,FALSE),VLOOKUP(TRIM(A122),[1]PROBLEMAS!$B$2:$I$122,8,FALSE)) -> JEHNIFFER PIRES | C122: =VLOOKUP(TRIM(Tabela2[[#This Row],[SEI]]),Tabela3[[Processo SEI]:[Objeto]],5,FALSE) -> PAVIMENTAÇÃO E RECAPEAMENTO EM NITERÓI E AEROPORTO – ITAPERUNA/RJ | D122: CONSTRUSAN | E122: ITAPERUNA | F122: ANDREIA VASQUES / ISADORA ROSALINO | G122: EXECUÇÃO | H122: NT | I122: =IFERROR(VLOOKUP(TRIM(Tabela2[[#This Row],[SEI]]),[1]Medições!$B$2:$H$48,7,FALSE),Tabela2[[#This Row],[STATUS_original]]) -> EXECUÇÃO
A123: 330018/000658/2022 | B123: =IFERROR(VLOOKUP(TRIM(A123),[1]Medições!$B$2:$I$48,8,FALSE),VLOOKUP(TRIM(A123),[1]PROBLEMAS!$B$2:$I$122,8,FALSE)) -> JEHNIFFER PIRES | C123: =VLOOKUP(TRIM(Tabela2[[#This Row],[SEI]]),Tabela3[[Processo SEI]:[Objeto]],5,FALSE) -> REVITALIZAÇÃO URBANA – BAIRRO VALÃO DO BARRO, SÃO SEBASTIÃO DO ALTO/RJ | D123: CONPLAN | E123: SÃO SEBASTIÃO DO ALTO | F123: ANDREIA VASQUES / ISADORA ROSALINO | G123: EXECUÇÃO | H123: NT | I123: =IFERROR(VLOOKUP(TRIM(Tabela2[[#This Row],[SEI]]),[1]Medições!$B$2:$H$48,7,FALSE),Tabela2[[#This Row],[STATUS_original]]) -> EXECUÇÃO
A124: 330001/001345/2025 | B124: =IFERROR(VLOOKUP(TRIM(A124),[1]Medições!$B$2:$I$48,8,FALSE),VLOOKUP(TRIM(A124),[1]PROBLEMAS!$B$2:$I$122,8,FALSE)) -> JEHNIFFER PIRES | C124: =VLOOKUP(TRIM(Tabela2[[#This Row],[SEI]]),Tabela3[[Processo SEI]:[Objeto]],5,FALSE) -> ADESÃO DE ATA DE REGISTRO DE PREÇO PARA SERVIÇOS DE URBANIZAÇÃO, DIVIDIDOS EM 4 LOTES POR REGIÕES, (EXECUÇÃO DE CONSTRUÇÃO/RECUPERAÇÃO DE CALÇADAS, CICLOVIAS E PAVIMENTOS DE DIVERSOS TRECHOS DESCONTÍNUOS DE VIAS NÃO CADASTRADAS EM LOGRADOUROS PÚBLICOS MUNICIPAIS) A SER IMPLEMENTADO NAS IMEDIAÇÕES DAS HABITAÇÕES DE INTERESSE SOCIAL OU EM ÁREAS CONFIGURADAS COMO DE ESPECIAL INTERESSE SOCIAL - LOTE IV (SERRANA e CENTRO NORTE) | D124: FAB MIX CONCRETOS | E124: CAMPOS DOS GOYTACAZES | F124: ANDREIA VASQUES / LUCIANA POSTIÇO | G124: EXECUÇÃO | H124: NT | I124: =IFERROR(VLOOKUP(TRIM(Tabela2[[#This Row],[SEI]]),[1]Medições!$B$2:$H$48,7,FALSE),Tabela2[[#This Row],[STATUS_original]]) -> ATA DE REGISTRO
A125: E-17/001/219/2018 | B125: =IFERROR(VLOOKUP(TRIM(A125),[1]Medições!$B$2:$I$48,8,FALSE),VLOOKUP(TRIM(A125),[1]PROBLEMAS!$B$2:$I$122,8,FALSE)) -> JEHNIFFER PIRES | C125: =VLOOKUP(TRIM(Tabela2[[#This Row],[SEI]]),Tabela3[[Processo SEI]:[Objeto]],5,FALSE) -> INTERVENÇÃO URBANÍSTICA E GEOTECNIA NA RUA MILTON MONNERAT | D125: SOPE ENGENHARIA | E125: BOM JARDIM | F125: ANDREIA VASQUES / ISADORA ROSALINO | G125: EXECUÇÃO | H125: CONT | I125: =IFERROR(VLOOKUP(TRIM(Tabela2[[#This Row],[SEI]]),[1]Medições!$B$2:$H$48,7,FALSE),Tabela2[[#This Row],[STATUS_original]]) -> EXECUÇÃO
A126: 330018/000568/2021 | B126: =IFERROR(VLOOKUP(TRIM(A126),[1]Medições!$B$2:$I$48,8,FALSE),VLOOKUP(TRIM(A126),[1]PROBLEMAS!$B$2:$I$122,8,FALSE)) -> LUIZ FILHO | C126: =VLOOKUP(TRIM(Tabela2[[#This Row],[SEI]]),Tabela3[[Processo SEI]:[Objeto]],5,FALSE) -> DRENAGEM E PAVIMENTAÇÃO EM DIVERSAS RUAS EM SANTA AMÉLIA, JAPERI-RJ | D126: CMAX | E126: JAPERI | F126: CAIO | G126: ACEITE PROVISORIO | H126: BX | I126: =IFERROR(VLOOKUP(TRIM(Tabela2[[#This Row],[SEI]]),[1]Medições!$B$2:$H$48,7,FALSE),Tabela2[[#This Row],[STATUS_original]]) -> ACEITE PROVISORIO
A127: 330018/000732/2021 | B127: =IFERROR(VLOOKUP(TRIM(A127),[1]Medições!$B$2:$I$48,8,FALSE),VLOOKUP(TRIM(A127),[1]PROBLEMAS!$B$2:$I$122,8,FALSE)) -> LUIZ FILHO | C127: =VLOOKUP(TRIM(Tabela2[[#This Row],[SEI]]),Tabela3[[Processo SEI]:[Objeto]],5,FALSE) -> DRENAGEM, PAVIMENTAÇÃO E SINALIZAÇÃO – MORADA DA BARRA, RESENDE-RJ | D127: COMAL | E127: RESENDE | F127: ARLINDO BASILIO / JOÃO RODRIGUES | G127: CONCLUIDA | H127: SL | I127: =IFERROR(VLOOKUP(TRIM(Tabela2[[#This Row],[SEI]]),[1]Medições!$B$2:$H$48,7,FALSE),Tabela2[[#This Row],[STATUS_original]]) -> CONCLUIDA
A128: 330018/000066/2022 | B128: =IFERROR(VLOOKUP(TRIM(A128),[1]Medições!$B$2:$I$48,8,FALSE),VLOOKUP(TRIM(A128),[1]PROBLEMAS!$B$2:$I$122,8,FALSE)) -> LUIZ FILHO | C128: =VLOOKUP(TRIM(Tabela2[[#This Row],[SEI]]),Tabela3[[Processo SEI]:[Objeto]],5,FALSE) -> GALERIAS DE ÁGUAS PLUVIAIS E ESGOTO NOS BAIRROS RETA E BENTO ARGON – COMENDADOR LEVY GASPARIAN/RJ | D128: FARO LTDA | E128: LEVY GASPARIAN | F128: JOÃO RODRIGUES / CAIO | G128: CONCLUIDA | H128: SL | I128: =IFERROR(VLOOKUP(TRIM(Tabela2[[#This Row],[SEI]]),[1]Medições!$B$2:$H$48,7,FALSE),Tabela2[[#This Row],[STATUS_original]]) -> CONCLUIDA
A129: 330018/000748/2022 | B129: =IFERROR(VLOOKUP(TRIM(A129),[1]Medições!$B$2:$I$48,8,FALSE),VLOOKUP(TRIM(A129),[1]PROBLEMAS!$B$2:$I$122,8,FALSE)) -> LUIZ FILHO | C129: =VLOOKUP(TRIM(Tabela2[[#This Row],[SEI]]),Tabela3[[Processo SEI]:[Objeto]],5,FALSE) -> REVESTIMENTO ASFÁLTICO, DRENAGEM E GALERIAS – BARRA DO PIRAÍ-RJ | D129: STATLED BRASIL | E129: BARRA DO PIRAÍ | F129: JOÃO RODRIGUES | G129: DISTRATO | H129: SL | I129: =IFERROR(VLOOKUP(TRIM(Tabela2[[#This Row],[SEI]]),[1]Medições!$B$2:$H$48,7,FALSE),Tabela2[[#This Row],[STATUS_original]]) -> DISTRATO
A130: 390005/000096/2021 | B130: =IFERROR(VLOOKUP(TRIM(A130),[1]Medições!$B$2:$I$48,8,FALSE),VLOOKUP(TRIM(A130),[1]PROBLEMAS!$B$2:$I$122,8,FALSE)) -> MARCUS | C130: =VLOOKUP(TRIM(Tabela2[[#This Row],[SEI]]),Tabela3[[Processo SEI]:[Objeto]],5,FALSE) -> CONSTRUÇÃO DE GALPÃO E READEQUAÇÃO DO HELIPONTO COMANDANTE ANDRÉ TAVARES DE CAMPOS | D130: ABBM | E130: RIO DE JANEIRO | G130: ACEITE DEFINITIVO | H130: ESPECIAIS | I130: =IFERROR(VLOOKUP(TRIM(Tabela2[[#This Row],[SEI]]),[1]Medições!$B$2:$H$48,7,FALSE),Tabela2[[#This Row],[STATUS_original]]) -> ACEITE DEFINITIVO
A131: Total | B131: =SUBTOTAL(103,Tabela2[GESTOR]) -> 129

Sheet GERAL
A1: Processo SEI | B1: Municipio | C1: Nº do contrato | D1: Fase | E1: Objeto | F1: Contratada | G1: Acumulado atual (%) | H1: Valor contrato (Atual) | I1: Acumulado | J1: Saldo Atual do Contrato | K1: Ordem de Início | L1: Prazo Final
A2: 170026/003032/2021 | B2: ANGRA DOS REIS | D2: PREPARAÇÃO | E2: REVITALIZAÇÃO DO CAMPO DE FUTEBOL E PRAÇA - CAMPO BELO, ANGRA DOS REIS/RJ | F2: Não existe na tabela Contratadas | G2: 0 | H2: 0 | I2: 0 | J2: 0 | K2: - | L2: -
A3: 170026/001374/2022 | B3: ANGRA DOS REIS | C3: 085/2022 | D3: CONCLUÍDA | E3: CONTENÇÃO E DRENAGEM - ILHA DO ARROZ, ANGRA DOS REIS/RJ | F3: BARRA NOVA ENGENHARIA LTDA | G3: 0.8916 | H3: 14782912 | I3: 13180256 | J3: 1602655.6 | K3: 44917 | L3: 45513
A4: 330018/000445/2023 | B4: ANGRA DOS REIS | C4: 003/2024 | D4: NÃO CONCLUÍDA | E4: RECOMPOSIÇÃO DA AV. BEIRA RIO - ANGRA DOS REIS/RJ | F4: OMEGA CONSTRUTORA E SERVICOS LTDA | G4: 0 | H4: 10134015 | I4: 0 | J4: 10134015 | K4: 45365 | L4: 45476
A5: 170026/001848/2022 | B5: ANGRA DOS REIS | C5: 064/2022 | D5: CONCLUÍDA | E5: CONTENÇÃO E DRENAGEM - PRAIA DAS ÉGUAS, ANGRA DOS REIS/RJ | F5: GEOSONDA S/A - EM RECUPERAÇÃO JUDICIAL | G5: 0.6744 | H5: 37535913 | I5: 25313733 | J5: 12222179 | K5: 44807 | L5: 45208
A6: 330001/001313/2024 | B6: ANGRA DOS REIS | D6: PREPARAÇÃO | E6: CONTENÇÃO E DRENAGEM - AV. BERTOLDO DA SILVA JORDÃO, MONSUABA - ANGRA DOS REIS/RJ | F6: Não existe na tabela Contratadas | G6: 0 | H6: 48244681 | I6: 0 | J6: 48244681 | K6: - | L6: -
A7: 170026/003819/2021 | B7: APERIBÉ | D7: PREPARAÇÃO | E7: PAVIMENTAÇÃO NOS BAIRROS DERANES, CAETANO E SERRINHA – APERIBÉ/RJ | F7: Não existe na tabela Contratadas | G7: 0 | H7: 7000 | I7: 0 | J7: 7000 | K7: - | L7: -
A8: 170026/002911/2022 | B8: APERIBÉ | D8: PREPARAÇÃO | E8: REFORMA DE PRÉDIO PARA CENTRO CULTURAL – APERIBÉ/RJ | F8: Não existe na tabela Contratadas | G8: 0 | H8: 2344484.9 | I8: 0 | J8: 2344484.9 | K8: - | L8: -
A9: 330001/001445/2024 | B9: APERIBÉ | D9: CONTRATAÇÃO (FASE INTERNA) | E9: REFORMA E ADEQUAÇÃO DO CENTRO CULTURAL – APERIBÉ/RJ | F9: Não existe na tabela Contratadas | G9: 0 | H9: 2570394.1 | I9: 0 | J9: 2570394.1 | K9: - | L9: -
A10: 170026/003264/2021 | B10: ARARUAMA | C10: 023/2022 | D10: CONCLUÍDA | E10: CONSTRUÇÃO DE ACOSTAMENTO, CICLOVIA E CALÇADA EM PRAIA SECA – ARARUAMA/RJ | F10: OMEGA CONSTRUTORA E SERVICOS LTDA | G10: 1 | H10: 4928388.1 | I10: 4928388.3 | J10: -0.17 | K10: 45478 | L10: 45327
A11: 170026/000477/2022 | B11: ARARUAMA | D11: PREPARAÇÃO | E11: PAVIMENTAÇÃO, URBANIZAÇÃO E DRENAGEM EM PARATY E FAZENDINHA – ARARUAMA/RJ | F11: Não existe na tabela Contratadas | G11: 0 | H11: 0 | I11: 0 | J11: 0 | K11: - | L11: -
A12: 170026/002945/2021 | B12: ARARUAMA | D12: PREPARAÇÃO | E12: DRENAGEM, PAVIMENTAÇÃO E URBANIZAÇÃO NA AV. DO CONTORNO E RUAS ADJACENTES – IGUABINHA, ARARUAMA/RJ | F12: Não existe na tabela Contratadas | G12: 0 | H12: 0 | I12: 0 | J12: 0 | K12: - | L12: -
A13: 170026/002953/2021 | B13: ARARUAMA | D13: PREPARAÇÃO | E13: CONSTRUÇÃO DE QUADRA POLIESPORTIVA NA ESCOLA VEREADOR MOYSÉS RAMALHO – ARARUAMA/RJ | F13: Não existe na tabela Contratadas | G13: 0 | H13: 0 | I13: 0 | J13: 0 | K13: - | L13: -
A14: 330001/000487/2025 | B14: ARARUAMA | D14: PREPARAÇÃO | E14: DRENAGEM E PAVIMENTAÇÃO NA FAZENDINHA | F14: Não existe na tabela Contratadas | G14: 0 | H14: 0 | I14: 0 | J14: 0 | K14: - | L14: -
A15: 170026/002950/2021 | B15: ARARUAMA | D15: PREPARAÇÃO | E15: CONSTRUÇÃO DE QUADRA POLIESPORTIVA NA ESCOLA CELINA MESQUITA PEDROSA – ARARUAMA/RJ | F15: Não existe na tabela Contratadas | G15: 0 | H15: 1283313.1 | I15: 0 | J15: 1283313.1 | K15: - | L15: -
A16: 170026/002066/2021 | B16: ARARUAMA | D16: PREPARAÇÃO | E16: DRENAGEM, PAVIMENTAÇÃO E URBANIZAÇÃO NA RUA OSCAR CLARK – FONTE LIMPA, ARARUAMA/RJ | F16: Não existe na tabela Contratadas | G16: 0 | H16: 2730917.6 | I16: 0 | J16: 2730917.6 | K16: - | L16: -
A17: 170026/001780/2022 | B17: ARARUAMA | D17: CONTRATAÇÃO (FASE INTERNA) | E17: PAVIMENTAÇÃO E DRENAGEM EM DIVERSAS VIAS DO 3º DISTRITO – ARARUAMA/RJ | F17: Não existe na tabela Contratadas | G17: 0 | H17: 25583969 | I17: 0 | J17: 25583969 | K17: - | L17: -
A18: 330001/001549/2025 | B18: ARARUAMA | D18: CONTRATAÇÃO (FASE INTERNA) | E18: ELABORAÇÃO DE PROJETO EXECUTIVO E REALIZAÇÃO DOS SERVIÇOS DE DRENAGEM, PAVIMENTAÇÃO, SINALIZAÇÃO HORIZONTAL E CALÇADA, NO BAIRRO FAZENDINHA (BACIA 2), NO MUNICÍPIO DE ARARUAMA/RJ. | F18: Não existe na tabela Contratadas | G18: 0 | H18: 67886819 | I18: 0 | J18: 67886819 | K18: - | L18: -
A19: 330001/001564/2025 | B19: ARARUAMA | D19: PREPARAÇÃO | E19: ELABORAÇÃO DE PROJETO EXECUTIVO E REALIZAÇÃO DOS SERVIÇOS DE DRENAGEM, PAVIMENTAÇÃO, SINALIZAÇÃO HORIZONTAL E CALÇADA, NO BAIRRO FAZENDINHA (BACIAS 1 E 3), NO MUNICÍPIO DE ARARUAMA/RJ. | F19: Não existe na tabela Contratadas | G19: 0 | H19: 71876187 | I19: 0 | J19: 71876187 | K19: - | L19: -
A20: 170026/000814/2021 | B20: AREAL | C20: 025/2021 | D20: TRANSFERIDA | E20: OBRAS DE INFRAESTRUTURA E MELHORIA VIÁRIA EM AREAL/RJ | F20: CONSTRUTORA MEDEIROS CARVALHO DE ALMEIDA EIRELI | G20: 0 | H20: 4473797.8 | I20: 0 | J20: 4473797.8 | K20: 44520 | L20: -
A21: 330001/001542/2025 | B21: AREAL | D21: CONTRATAÇÃO (FASE INTERNA) | E21: CONTRATAÇÃO DE EMPRESA ESPECIALIZADA PARA EXECUÇÃO DE OBRAS PARA ADEQUAÇÃO DE ACESSOS VIÁRIOS NO MUNICÍPIO DE AREAL/RJ | F21: Não existe na tabela Contratadas | G21: 0 | H21: 5124881.8 | I21: 0 | J21: 5124881.8 | K21: - | L21: -
A22: 170026/000278/2021 | B22: ARMAÇÃO DOS BÚZIOS | D22: PREPARAÇÃO | E22: CONSTRUÇÃO DO COLÉGIO ESTADUAL PROFESSOR FRANCISCO MARIA DE SOUZA - BÚZIOS/RJ | F22: Não existe na tabela Contratadas | G22: 0 | H22: 11806978 | I22: 0 | J22: 11806978 | K22: - | L22: -
A23: 330018/001612/2022 | B23: ARMAÇÃO DOS BÚZIOS | D23: TRANSFERIDA | E23: PAVIMENTAÇÃO, DRENAGEM, SINALIZAÇÃO E ILUMINAÇÃO NA ESTRADA DA FAZENDINHA – BÚZIOS/RJ | F23: CONSORCIO FACHADA MIS R2X/TANGRAN (CONSTRUTORA R2X E TANGRAN ENGENHARIA) | G23: 0 | H23: 27621068 | I23: 0 | J23: 27621068 | K23: - | L23: -
A24: 330001/001910/2024 | B24: BARRA DO PIRAÍ | D24: PREPARAÇÃO | E24: CONTENÇÃO DE TALUDE – BAIRROS AREAL E BOA SORTE – BARRA DO PIRAÍ-RJ | F24: Não existe na tabela Contratadas | G24: 0 | H24: 11230.35 | I24: 0 | J24: 11230.35 | K24: - | L24: -
A25: 170026/000511/2022 | B25: BARRA DO PIRAÍ | D25: PREPARAÇÃO | E25: REFORMA DE PRAÇA – BAIRRO OFICINAS VELHAS – BARRA DO PIRAÍ-RJ | F25: Não existe na tabela Contratadas | G25: 0 | H25: 556051.81 | I25: 0 | J25: 556051.81 | K25: - | L25: -
A26: 170026/000516/2022 | B26: BARRA DO PIRAÍ | D26: PREPARAÇÃO | E26: CONSTRUÇÃO DA PRAÇA NO NOVO CONJUNTO HABITACIONAL, VAGEM ALEGRE, BARRA DO PIRAÍ | F26: Não existe na tabela Contratadas | G26: 0 | H26: 1028513.4 | I26: 0 | J26: 1028513.4 | K26: - | L26: -
A27: 170026/000515/2022 | B27: BARRA DO PIRAÍ | D27: PREPARAÇÃO | E27: REFORMA DA PRAÇA – VARGEM ALEGRE – BARRA DO PIRAÍ-RJ | F27: Não existe na tabela Contratadas | G27: 0 | H27: 1167726.2 | I27: 0 | J27: 1167726.2 | K27: - | L27: -
A28: 170026/000513/2022 | B28: BARRA DO PIRAÍ | D28: PREPARAÇÃO | E28: REFORMA DA PRAÇA PEDRO CUNHA – CENTRO – BARRA DO PIRAÍ-RJ | F28: Não existe na tabela Contratadas | G28: 0 | H28: 3722694.3 | I28: 0 | J28: 3722694.3 | K28: - | L28: -
A29: 170026/000514/2022 | B29: BARRA DO PIRAÍ | D29: PREPARAÇÃO | E29: REFORMA DAS PRAÇAS E CAMPOS NA RUA PRESIDENTE COSTA E SILVA, CALIFÓRNIA, BARRA DO PIRAÍ-RJ | F29: Não existe na tabela Contratadas | G29: 0 | H29: 4868256.2 | I29: 0 | J29: 4868256.2 | K29: - | L29: -
A30: 170026/001999/2022 | B30: BARRA DO PIRAÍ | D30: PREPARAÇÃO | E30: REFORMA DO CIEP 428 PROFESSORA MARIANA COELHO, VARGEM ALEGRE, BARRA DO PIRAÍ-RJ | F30: Não existe na tabela Contratadas | G30: 0 | H30: 5578284.2 | I30: 0 | J30: 5578284.2 | K30: - | L30: -
A31: 170026/001998/2022 | B31: BARRA DO PIRAÍ | D31: PREPARAÇÃO | E31: REFORMA DO CIEP 284 – DISTRITO DA CALIFÓRNIA – BARRA DO PIRAÍ-RJ | F31: Não existe na tabela Contratadas | G31: 0 | H31: 5922938.9 | I31: 0 | J31: 5922938.9 | K31: - | L31: -
A32: 170026/000517/2022 | B32: BARRA DO PIRAÍ | D32: PREPARAÇÃO | E32: CONTRATAÇÃO DE EMPRESA PARA ELABORAÇÃO E EXECUÇÃO DE PROJETOS E OBRAS DE CALÇADAS NO CENTRO DE BARRA DO PIRAÍ | F32: Não existe na tabela Contratadas | G32: 0 | H32: 6373265.8 | I32: 0 | J32: 6373265.8 | K32: - | L32: -
A33: 330001/001080/2025 | B33: BARRA DO PIRAÍ | C33: 014/2025 | D33: EXECUÇÃO | E33: REVESTIMENTO ASFÁLTICO, DRENAGEM, CONSTRUÇÃO DE GALERIAS DE ÁGUAS PLUVIAIS, URBANIZAÇÃO, CICLOFAIXA E ESTABILIZAÇÃO DE TALUDE, MUNICÍPIO DE BARRA DO PIRAÍ - RJJ | F33: CONSTRUTORA AXIAL LTDA | G33: 0.2004 | H33: 18990163 | I33: 3806174.7 | J33: 15183988 | K33: 45868 | L33: 46228
A34: 330018/000748/2022 | B34: BARRA DO PIRAÍ | C34: 013/2023 | D34: NÃO CONCLUÍDA | E34: REVESTIMENTO ASFÁLTICO, DRENAGEM E GALERIAS – BARRA DO PIRAÍ-RJ | F34: STATLED BRASIL CONSTRUTORA E PARTICIPACOES S.A. | G34: 0.0076 | H34: 16774604 | I34: 127835.64 | J34: 16646768 | K34: 45100 | L34: 45460
A35: 170026/003250/2021 | B35: BARRA MANSA | C35: 056/2022 | D35: EXECUÇÃO | E35: RECAPEAMENTO, PAVIMENTAÇÃO E CONTENÇÃO – BARRA MANSA-RJ | F35: CONSTRUTORA LYTORANEA S A | G35: 1 | H35: 5581731.3 | I35: 5581730.3 | J35: 1 | K35: 44777 | L35: 45348
A36: 170026/003814/2021 | B36: BARRA MANSA | D36: PREPARAÇÃO | E36: CONTENÇÃO DE TALUDE – RUA MAURO GRANATO – BARRA MANSA-RJ | F36: Não existe na tabela Contratadas | G36: 0 | H36: 1500 | I36: 0 | J36: 1500 | K36: - | L36: -
A37: 170026/001812/2021 | B37: BARRA MANSA | C37: 027/2021 | D37: CONCLUÍDA | E37: CONSTRUÇÃO DE PONTE - BARRA MANSA/RJ | F37: PREMAG - SISTEMA DE CONSTRUÇÕES LTDA | G37: 0.9902 | H37: 5312585.6 | I37: 5260332.3 | J37: 52253.31 | K37: 44536 | L37: 45289
A38: 330018/001062/2022 | B38: BARRA MANSA | C38: 063/2022 | D38: EXECUÇÃO | E38: PAVIMENTAÇÃO E DRENAGEM – AV. PRESIDENTE KENNEDY – BARRA MANSA-RJ | F38: STATLED BRASIL CONSTRUTORA I LTDA (subsidiária) | G38: 0.9713 | H38: 7795660.5 | I38: 7571952.3 | J38: 223708.17 | K38: 44909 | L38: 46144
A39: 330001/000715/2024 | B39: BARRA MANSA | C39: 005/2024 | D39: EXECUÇÃO | E39: USINAGEM, TRANSPORTE E PAVIMENTAÇÃO EM CBUQ – BARRA MANSA/RJ | F39: H J RODRIGUES MELO LTDA | G39: 0.8916 | H39: 7234583.8 | I39: 6450491.3 | J39: 784092.46 | K39: 45425 | L39: 45999
A40: 330001/001925/2025 | B40: BARRA MANSA | D40: PREPARAÇÃO | E40: DECK ÀS MARGENS DO RIO PARAÍBA DO SUL | F40: Não existe na tabela Contratadas | G40: - | H40: 1439881.5 | I40: 0 | J40: 1439881.5 | K40: - | L40: -
A41: 330001/000206/2026 | B41: BARRA MANSA | D41: PREPARAÇÃO | E41: REURBANIZAÇÃO E SENSORIAL DO TRECHO ENTRE AS RUAS JOSÉ ALVES DE SOUZA E SEBASTIÃO GOMES DE BRITO SOBRINHO - VILA NOVA | F41: Não existe na tabela Contratadas | G41: - | H41: 2041166 | I41: 0 | J41: 2041166 | K41: - | L41: -
A42: 330018/000053/2023 | B42: BARRA MANSA | C42: 013/2024 | D42: EXECUÇÃO | E42: RECUPERAÇÃO DE PAVIMENTAÇÃO – BARRA MANSA-RJ (#FUNDO SOBERADO) | F42: ABRE CONSTRUÇÃO LTDA | G42: 0.8457 | H42: 36782152 | I42: 31106159 | J42: 5675993.1 | K42: 45566 | L42: 46228
A43: 170026/003298/2022 | B43: BARRA MANSA | D43: PREPARAÇÃO | E43: AMPLIAÇÃO DO ABASTECIMENTO DE ÁGUA – BAIRROS DE BARRA MANSA-RJ | F43: Não existe na tabela Contratadas | G43: 0 | H43: 7000000 | I43: 0 | J43: 7000000 | K43: - | L43: -
A44: 330018/001108/2022 | B44: BARRA MANSA | C44: 062/2022 | D44: NÃO CONCLUÍDA | E44: USINAGEM E PAVIMENTAÇÃO – BAIRROS DE BARRA MANSA-RJ | F44: CONSTRUTORA MACADAME LTDA | G44: 0.4067 | H44: 11928823 | I44: 4852042.8 | J44: 7076780.2 | K44: 44903 | L44: 45239
A45: 170026/003817/2021 | B45: BARRA MANSA | D45: PREPARAÇÃO | E45: IMPLANTAÇÃO DE ADUTORA – BAIRROS BOA SORTE E PARAÍSO – BARRA MANSA-RJ | F45: Não existe na tabela Contratadas | G45: 0 | H45: 7218644.4 | I45: 0 | J45: 7218644.4 | K45: - | L45: -
A46: 330018/001109/2022 | B46: BARRA MANSA | C46: 008/2023 | D46: EXECUÇÃO | E46: CANALIZAÇÃO E URBANIZAÇÃO – AV. PINHEIROS – BARRA MANSA-RJ | F46: STATLED BRASIL CONSTRUTORA E PARTICIPACOES S.A. | G46: 0.5746 | H46: 22825141 | I46: 13115142 | J46: 9709999.5 | K46: 45019 | L46: 46193
A47: 460001/002017/2023 | B47: BARRA MANSA | D47: CONTRATAÇÃO (FASE INTERNA) | E47: MICRODRENAGEM, CALÇADAS E PAVIMENTAÇÃO – BAIRROS DE BARRA MANSA-RJ | F47: Não existe na tabela Contratadas | G47: 0 | H47: 40495439 | I47: 0 | J47: 40495439 | K47: - | L47: -
A48: 330018/000311/2022 | B48: BARRA MANSA | D48: PREPARAÇÃO | E48: INFRAESTRUTURA E PAVIMENTAÇÃO – BAIRROS DE BARRA MANSA-RJ | F48: Não existe na tabela Contratadas | G48: 0 | H48: 53112166 | I48: 0 | J48: 53112166 | K48: - | L48: -
A49: 170026/001440/2022 | B49: BARRA MANSA | D49: PREPARAÇÃO | E49: MODERNIZAÇÃO E INFRAESTRUTURA – PARQUE DA CIDADE – BARRA MANSA-RJ | F49: Não existe na tabela Contratadas | G49: 0 | H49: 73545012 | I49: 0 | J49: 73545012 | K49: - | L49: -
A50: 330018/000887/2022 | B50: BELFORD ROXO | C50: 015/2023 | D50: CONCLUÍDA | E50: ESTABILIZAÇÃO DE ENCOSTA DA RUA DIAMANTINA - BELFORD ROXO | F50: SEEL SERVICOS ESPECIAIS DE ENGENHARIA LTDA | G50: 0.999 | H50: 7155724.4 | I50: 7148655.6 | J50: 7068.79 | K50: 45314 | L50: 45617
A51: 330018/001213/2022 | B51: BELFORD ROXO | C51: 004/2024 | D51: EXECUÇÃO | E51: PONTE EM CONCRETO PROTENDIDO COM DRENAGEM – BELFORD ROXO/RJ | F51: SEEL SERVICOS ESPECIAIS DE ENGENHARIA LTDA | G51: 0.8856 | H51: 6765672.3 | I51: 5991696.6 | J51: 773975.71 | K51: 45398 | L51: 46062
A52: 330018/000756/2022 | B52: BELFORD ROXO | D52: CONTRATAÇÃO (ADJUDICADA) | E52: ESTABILIZAÇÃO DE ENCOSTA – MURO DE CONTENÇÃO – BELFORD ROXO-RJ | F52: Não existe na tabela Contratadas | G52: 0 | H52: 2461488.3 | I52: 0 | J52: 2461488.3 | K52: - | L52: -
A53: 330018/001643/2022 | B53: BELFORD ROXO | D53: CONTRATAÇÃO (FASE INTERNA) | E53: CONTENÇÃO NA VILA SANTA RITA - BELFORD ROXO/RJ | F53: Não existe na tabela Contratadas | G53: 0 | H53: 2861863 | I53: 0 | J53: 2861863 | K53: - | L53: -
A54: 330018/000773/2022 | B54: BELFORD ROXO | D54: PREPARAÇÃO | E54: REFORMA DE CONJUNTO HABITACIONAL NO BAIRRO SANTO ANTÔNIO DA PRATA, BELFORD ROXO/RJ | F54: Não existe na tabela Contratadas | G54: 0 | H54: 5034459.6 | I54: 0 | J54: 5034459.6 | K54: - | L54: -
A55: 330018/002047/2022 | B55: BELFORD ROXO | D55: PREPARAÇÃO | E55: PROJETO E OBRAS DE DRENAGEM E PAVIMENTAÇÃO NA AV. NOVA AURORA, BELFORD ROXO/RJ | F55: Não existe na tabela Contratadas | G55: 0 | H55: 5220803.8 | I55: 0 | J55: 5220803.8 | K55: - | L55: -
A56: 330018/001252/2022 | B56: BELFORD ROXO | D56: CONTRATAÇÃO (FASE INTERNA) | E56: DRENAGEM, PAVIMENTAÇÃO E CONTENÇÃO EM PIAM - BELFORD ROXO/RJ | F56: Não existe na tabela Contratadas | G56: 0 | H56: 16294233 | I56: 0 | J56: 16294233 | K56: - | L56: -
A57: 330001/000156/2025 | B57: BELFORD ROXO | D57: PREPARAÇÃO | E57: DRENAGEM E PAVIMENTAÇÃO – VILA CLÁUDIA E SHANGRILÁ, BELFORD ROXO/RJ | F57: Não existe na tabela Contratadas | G57: 0 | H57: 1.4827651e+08 | I57: 0 | J57: 1.4827651e+08 | K57: - | L57: -
A58: 170026/002087/2021 | B58: BOM JARDIM | D58: PREPARAÇÃO | E58: RECUPERAÇÃO DE GALERIA DE DRENAGEM – BOM JARDIM/RJ | F58: Não existe na tabela Contratadas | G58: 0 | H58: 759410.41 | I58: 0 | J58: 759410.41 | K58: - | L58: -
A59: 170026/003228/2021 | B59: BOM JARDIM | D59: PREPARAÇÃO | E59: QUADRA POLIESPORTIVA – JARDIM BOA ESPERANÇA, BOM JARDIM | F59: Não existe na tabela Contratadas | G59: 0 | H59: 881299.43 | I59: 0 | J59: 881299.43 | K59: - | L59: -
A60: E-17/001/219/2018 | B60: BOM JARDIM | C60: 018/2025 | D60: EXECUÇÃO | E60: INTERVENÇÃO URBANÍSTICA E GEOTECNIA NA RUA MILTON MONNERAT | F60: SOPE SOCIEDADE DE OBRAS E PROJETOS DE ENGENHARIA LTDA. | G60: 0 | H60: 2742607.7 | I60: 0 | J60: 2742607.7 | K60: 45917 | L60: 46097
A61: 330018/000848/2021 | B61: BOM JARDIM | D61: TRANSFERIDA | E61: PAVIMENTAÇÃO E DRENAGEM EM BOM JARDIM/RJ (Ruas Presidente Vargas e Nilo Peçanha) | F61: Não existe na tabela Contratadas | G61: 0 | H61: 6826938.6 | I61: 0 | J61: 6826938.6 | K61: - | L61: -
A62: 170026/000631/2021 | B62: BOM JESUS DO ITABAPOANA | D62: PREPARAÇÃO | E62: REFORMA DE QUADRA E BANHEIROS - BELA VISTA - BOM JESUS/RJ | F62: Não existe na tabela Contratadas | G62: 0 | H62: 0 | I62: 0 | J62: 0 | K62: - | L62: -
A63: 170026/000636/2021 | B63: BOM JESUS DO ITABAPOANA | D63: PREPARAÇÃO | E63: CALÇAMENTO COM DRENAGEM - RUA CANTÃO - BOM JESUS/RJ | F63: Não existe na tabela Contratadas | G63: 0 | H63: 0 | I63: 0 | J63: 0 | K63: - | L63: -
A64: 170026/000637/2021 | B64: BOM JESUS DO ITABAPOANA | D64: PREPARAÇÃO | E64: CALÇAMENTO COM DRENAGEM - RUA MARIA TULIBA - BOM JESUS/RJ | F64: Não existe na tabela Contratadas | G64: 0 | H64: 0 | I64: 0 | J64: 0 | K64: - | L64: -
A65: 170026/000638/2021 | B65: BOM JESUS DO ITABAPOANA | D65: PREPARAÇÃO | E65: CALÇAMENTO COM DRENAGEM - RUA MARIA APARECIDA R. MARTINS - BOM JESUS/RJ | F65: Não existe na tabela Contratadas | G65: 0 | H65: 0 | I65: 0 | J65: 0 | K65: - | L65: -
A66: 170026/000643/2021 | B66: BOM JESUS DO ITABAPOANA | D66: PREPARAÇÃO | E66: PAVIMENTAÇÃO COM DRENAGEM - BOM JESUS DO ITABAPOANA/RJ | F66: Não existe na tabela Contratadas | G66: 0 | H66: 0 | I66: 0 | J66: 0 | K66: - | L66: -
A67: 170026/000646/2021 | B67: BOM JESUS DO ITABAPOANA | D67: PREPARAÇÃO | E67: REFORMA DA PRAÇA JOÃO CATARINA - PIRAPETINGA - BOM JESUS/RJ | F67: Não existe na tabela Contratadas | G67: 0 | H67: 0 | I67: 0 | J67: 0 | K67: - | L67: -
A68: 170026/001389/2021 | B68: BOM JESUS DO ITABAPOANA | D68: PREPARAÇÃO | E68: URBANIZAÇÃO E QUADRA POLIESPORTIVA - USINA SANTA IZABEL - BOM JESUS/RJ | F68: Não existe na tabela Contratadas | G68: 0 | H68: 0 | I68: 0 | J68: 0 | K68: - | L68: -
A69: 170026/003743/2021 | B69: BOM JESUS DO ITABAPOANA | D69: PREPARAÇÃO | E69: REURBANIZAÇÃO DO CENTRO - BOM JESUS DO ITABAPOANA/RJ | F69: Não existe na tabela Contratadas | G69: 0 | H69: 0 | I69: 0 | J69: 0 | K69: - | L69: -
A70: 170026/003744/2021 | B70: BOM JESUS DO ITABAPOANA | D70: PREPARAÇÃO | E70: REVITALIZAÇÃO DO LAGO - SANTA MARIA - BOM JESUS/RJ | F70: Não existe na tabela Contratadas | G70: 0 | H70: 0 | I70: 0 | J70: 0 | K70: - | L70: -
A71: 170026/003745/2021 | B71: BOM JESUS DO ITABAPOANA | D71: PREPARAÇÃO | E71: REFORMA DA PRAÇA E QUADRA JOSÉ CANTO MASCARENHAS - BOM JESUS/RJ | F71: Não existe na tabela Contratadas | G71: 0 | H71: 0 | I71: 0 | J71: 0 | K71: - | L71: -
A72: 170026/003746/2021 | B72: BOM JESUS DO ITABAPOANA | D72: PREPARAÇÃO | E72: PISTA DE CAMINHADA - LOTEAMENTO SANTA EDWIRGES - BOM JESUS/RJ | F72: Não existe na tabela Contratadas | G72: 0 | H72: 0 | I72: 0 | J72: 0 | K72: - | L72: -
... A95: 170026/001114/2022 | B95: CACHOEIRAS DE MACACU | D95: PREPARAÇÃO | E95: PRAÇA LOURIVAL – JAPUÍBA, CACHOEIRAS DE MACACU | F95: Não existe na tabela Contratadas | G95: 0 | H95: 556775.13 | I95: 0 | J95: 556775.13 | K95: - | L95: -
A96: 170026/001116/2022 | B96: CACHOEIRAS DE MACACU | C96: 078/2022 | D96: TRANSFERIDA | E96: IMPLANTAÇÃO DA PRAÇA VILAGE JAPUIBA, CACHOEIRAS DE MACACU/RJ | F96: MCJL ENGENHARIA E SERVIÇOS LTDA | G96: 0.3312 | H96: 1115127.9 | I96: 369283.08 | J96: 745844.85 | K96: 45021 | L96: -
A97: 170026/001870/2021 | B97: CACHOEIRAS DE MACACU | D97: PREPARAÇÃO | E97: REFORMA DE PRAÇAS – VILAGE JAPUÍBA, AGRO BRASIL E SÃO JOSÉ - CACHOEIRAS DE MACACU | F97: Não existe na tabela Contratadas | G97: 0 | H97: 758485.14 | I97: 0 | J97: 758485.14 | K97: - | L97: -
A98: 170026/001112/2022 | B98: CACHOEIRAS DE MACACU | D98: PREPARAÇÃO | E98: IMPLANTAÇÃO DA PRAÇA AGRO BRASIL – CACHOEIRAS DE MACACU | F98: Não existe na tabela Contratadas | G98: 0 | H98: 824623.75 | I98: 0 | J98: 824623.75 | K98: - | L98: -
A99: 170026/000427/2022 | B99: CACHOEIRAS DE MACACU | D99: PREPARAÇÃO | E99: CONSTRUÇÃO DA PRAÇA VILAGE JAPUÍBA – CACHOEIRAS DE MACACU | F99: Não existe na tabela Contratadas | G99: 0 | H99: 1444813.1 | I99: 0 | J99: 1444813.1 | K99: - | L99: -
A100: 330018/001340/2022 | B100: CACHOEIRAS DE MACACU | D100: TRANSFERIDA | E100: CICLOVIA EM BETEL, CACHOEIRAS DE MACACU/RJ | F100: Não existe na tabela Contratadas | G100: 0 | H100: 1525973.4 | I100: 0 | J100: 1525973.4 | K100: - | L100: -
A101: 170026/001654/2022 | B101: CACHOEIRAS DE MACACU | C101: 089/2022 | D101: TRANSFERIDA | E101: OBRAS DE DRENAGEM E PAVIMENTAÇÃO EM GUARARAPES, CACHOEIRAS DE MACACU/RJ | F101: CONSTRUTORA SÉRGIO PORTO LTDA | G101: 0.2666 | H101: 5766225.8 | I101: 1537527.6 | J101: 4228698.1 | K101: 45021 | L101: -
A102: 330018/000511/2021 | B102: CACHOEIRAS DE MACACU | D102: PREPARAÇÃO | E102: DRENAGEM, ESGOTO E PAVIMENTAÇÃO – EXPANSÃO, CACHOEIRAS DE MACACU | F102: Não existe na tabela Contratadas | G102: 0 | H102: 5817569 | I102: 0 | J102: 5817569 | K102: - | L102: -
A103: 330018/001635/2022 | B103: CACHOEIRAS DE MACACU | D103: TRANSFERIDA | E103: DRENAGEM, PAVIMENTAÇÃO E MEIO-FIO EM JAPUÍBA, CACHOEIRAS DE MACACU/RJ | F103: Não existe na tabela Contratadas | G103: 0 | H103: 13328414 | I103: 0 | J103: 13328414 | K103: - | L103: -
A104: 330018/001605/2022 | B104: CACHOEIRAS DE MACACU | D104: TRANSFERIDA | E104: DRENAGEM, PAVIMENTAÇÃO E MEIO-FIO EM PAPUCAIA, CACHOEIRAS DE MACACU/RJ | F104: Não existe na tabela Contratadas | G104: 0 | H104: 17028552 | I104: 0 | J104: 17028552 | K104: - | L104: -
A105: 330018/001787/2022 | B105: CACHOEIRAS DE MACACU | D105: TRANSFERIDA | E105: OBRAS DE PAVIMENTAÇÃO E DRENAGEM EM PAPUCAIA, CACHOEIRAS DE MACACU/RJ | F105: Não existe na tabela Contratadas | G105: 0 | H105: 18170954 | I105: 0 | J105: 18170954 | K105: - | L105: -
A106: 330018/001345/2022 | B106: CACHOEIRAS DE MACACU | C106: 007/2023 | D106: TRANSFERIDA | E106: RECUPERAÇÃO DE PAVIMENTAÇÃO - CACHOEIRAS DE MACACU-RJ | F106: CONSTRUTORA LYTORANEA S A | G106: 0.3739 | H106: 30870280 | I106: 11542776 | J106: 19327505 | K106: 45005 | L106: -
A107: 170026/002283/2022 | B107: CACHOEIRAS DE MACACU | D107: PREPARAÇÃO | E107: OBRAS DE CONTENÇÃO E DRENAGEM – CACHOEIRAS DE MACACU | F107: Não existe na tabela Contratadas | G107: 0 | H107: 62232667 | I107: 0 | J107: 62232667 | K107: - | L107: -
A108: 330018/000613/2022 | B108: CACHOEIRAS DE MACACU | D108: PREPARAÇÃO | E108: REFORMA E DUPLICAÇÃO DE PONTE – CACHOEIRA DE MACACU | F108: Não existe na tabela Contratadas | G108: 0 | H108: 83810000 | I108: 0 | J108: 83810000 | K108: - | L108: -
A109: 170026/001485/2022 | B109: CAMBUCI | D109: PREPARAÇÃO | E109: CALÇAMENTO COM BLOCO INTERTRAVADO EM 10 RUAS - CAMBUCI/RJ | F109: Não existe na tabela Contratadas | G109: 0 | H109: 6134038.6 | I109: 0 | J109: 6134038.6 | K109: - | L109: -
A110: 330018/001003/2022 | B110: CAMBUCI | D110: CONTRATAÇÃO (FASE INTERNA) | E110: DRENAGEM, PAVIMENTAÇÃO E ESTRUTURAÇÃO DE LOGRADOUROS - CAMBUCI/RJ | F110: Não existe na tabela Contratadas | G110: 0 | H110: 21998317 | I110: 0 | J110: 21998317 | K110: - | L110: -
A111: 330001/000492/2025 | B111: CAMPOS DOS GOYTACAZES | D111: PREPARAÇÃO | E111: PROJETOS EXECUTIVOS E RECAPEAMENTO VIÁRIO EM CAMPOS | G111: - | H111: 0 | I111: 0 | J111: 0 | K111: - | L111: -
A112: 330001/001072/2025 | B112: CAMPOS DOS GOYTACAZES | D112: PREPARAÇÃO | E112: PAVIMENTAÇÃO E DRENAGEM EM PORTO BELO, VILA MENEZES E VILA MANHÃES, COM ELABORAÇÃO DO PROJETO EXECUTIVO- CAMPOS DOS GOYTACAZES | G112: - | H112: 0 | I112: 0 | J112: 0 | K112: - | L112: -
A113: 330018/000619/2021 | B113: CAMPOS DOS GOYTACAZES | C113: 011/2022 | D113: EXECUÇÃO | E113: PAVIMENTAÇÃO, URBANIZAÇÃO E DRENAGEM EM PARQUE SARAIVA - CAMPOS | F113: CONSORCIO PARQUE SARAIVA ( COFRANZA CONSTRUTORA LTDA, CONSTRUSAN SERVIÇOS INDUSTRIAIS LTDA, CONSTRUTORA AVENIDA LTDA, IMBEG- IMBE ENGENHARIA LTDA) | G113: 0.9954 | H113: 32464770 | I113: 32314428 | J113: 150341.88 | K113: 44697 | L113: 45972
A114: 330018/000156/2022 | B114: CAMPOS DOS GOYTACAZES | C114: 023/2022 | D114: CONCLUÍDA | E114: PAVIMENTAÇÃO, ÁGUA, ESGOTO E DRENAGEM EM FAROL DE SÃO THOMÉ - CAMPOS | F114: MECANORTE CONSTRUCOES E EMPREENDIMENTOS LTDA | G114: 0.94 | H114: 44149152 | I114: 41500959 | J114: 2648192 | K114: 44763 | L114: 45999
A115: 460001/000251/2023 | B115: CAMPOS DOS GOYTACAZES | C115: 020/2023 | D115: CONCLUÍDA | E115: RECOMPOSIÇÃO DO DIQUE E MARGEM DO RIO PARAÍBA DO SUL - CAMPOS DOS GOYTACAZES/RJ | F115: DRV ENGENHARIA - EIRELI | G115: 0.773 | H115: 16880240 | I115: 13048537 | J115: 3831703.5 | K115: 45034 | L115: 45253
A116: 330001/001345/2025 | B116: CAMPOS DOS GOYTACAZES | C116: 025/2025 | D116: ATA DE REGISTRO | E116: ADESÃO DE ATA DE REGISTRO DE PREÇO PARA SERVIÇOS DE URBANIZAÇÃO, DIVIDIDOS EM 4 LOTES POR REGIÕES, (EXECUÇÃO DE CONSTRUÇÃO/RECUPERAÇÃO DE CALÇADAS, CICLOVIAS E PAVIMENTOS DE DIVERSOS TRECHOS DESCONTÍNUOS DE VIAS NÃO CADASTRADAS EM LOGRADOUROS PÚBLICOS MUNICIPAIS) A SER IMPLEMENTADO NAS IMEDIAÇÕES DAS HABITAÇÕES DE INTERESSE SOCIAL OU EM ÁREAS CONFIGURADAS COMO DE ESPECIAL INTERESSE SOCIAL - LOTE IV (SERRANA e CENTRO NORTE) | F116: FAB MIX CONCRETOS LTDA | G116: 0 | H116: 5054505.2 | I116: 0 | J116: 5054505.2 | K116: - | L116: 46312
A117: 330018/000695/2021 | B117: CAMPOS DOS GOYTACAZES | C117: 044/2022 | D117: EXECUÇÃO | E117: REVESTIMENTO ASFÁLTICO E DRENAGEM EM PORTO BELO –EM CAMPOS/RJ | F117: ALBERTO COUTO ALVES - BRASIL LTDA. | G117: 0.5163 | H117: 31022838 | I117: 16018051 | J117: 15004787 | K117: 45309 | L117: 46392
A118: 330018/000694/2021 | B118: CAMPOS DOS GOYTACAZES | C118: 059/2022 | D118: EXECUÇÃO | E118: PAVIMENTAÇÃO, URBANIZAÇÃO E DRENAGEM NOS BAIRROS DE CAMPOS | F118: IMBEG - IMBE ENGENHARIA LTDA | G118: 0.6608 | H118: 48872552 | I118: 32294745 | J118: 16577807 | K118: 44875 | L118: 46375
A119: 170026/002043/2021 | B119: CAMPOS DOS GOYTACAZES | C119: 054/2022 | D119: NÃO CONCLUÍDA | E119: PROJETOS EXECUTIVOS E RECAPEAMENTO VIÁRIO EM CAMPOS | F119: CONSTRUTORA METROPOLITANA S A | G119: 0.7193 | H119: 89008311 | I119: 64026819 | J119: 24981491 | K119: 44789 | L119: 45510
A120: 330018/001702/2022 | B120: CAMPOS DOS GOYTACAZES | D120: PREPARAÇÃO | E120: PAVIMENTAÇÃO E URBANIZAÇÃO NO PARQUE FAZENDA GOIABAL | G120: 0 | H120: 26911606 | I120: 0 | J120: 26911606 | K120: - | L120: -
A121: 330018/000962/2021 | B121: CAMPOS DOS GOYTACAZES | D121: PREPARAÇÃO | E121: PAVIMENTAÇÃO E DRENAGEM NO BAIRRO TAPERA – CAMPOS DOS GOYTACAZES/RJ | F121: Não existe na tabela Contratadas | G121: 0 | H121: 30877043 | I121: 0 | J121: 30877043 | K121: - | L121: -
A122: 330018/000760/2021 | B122: CAMPOS DOS GOYTACAZES | D122: PREPARAÇÃO | E122: OBRA DE CONSTRUÇÃO DO “DIQUE DA BOIANGA” SITUADO NA LOCALIDADE DE TRÊS VENDAS, VALÃO DA ONÇA EM CAMPOS DOS GOYTACAZES – RJ | F122: Não existe na tabela Contratadas | G122: 0 | H122: 31201068 | I122: 0 | J122: 31201068 | K122: - | L122: -
...
